<DOMSymbolItem xmlns:xsi="http://www.w3.org/2001/XMLSchema-instance" xmlns="http://ns.adobe.com/xfl/2008/" name="Symbol 8" itemID="54846269-00000254" lastModified="1417962097">
  <timeline>
    <DOMTimeline name="Symbol 8">
      <layers>
        <DOMLayer name="Layer 1" color="#4FFF4F">
          <frames>
            <DOMFrame index="0" keyMode="9728">
              <elements>
                <DOMShape>
                  <fills>
                    <FillStyle index="1">
                      <SolidColor alpha="0.976470588235294"/>
                    </FillStyle>
                    <FillStyle index="2">
                      <SolidColor color="#1A1717" alpha="0.976470588235294"/>
                    </FillStyle>
                    <FillStyle index="3">
                      <SolidColor color="#FFFFFF" alpha="0.976470588235294"/>
                    </FillStyle>
                  </fills>
                  <edges>
                    <Edge fillStyle1="1" edges="!2238 807[2257 830 2265 869!2265 869[2274 918 2263 954!2263 954[2247 1002 2197 1002!2197 1002[1686 1002 1451 928!1451 928[1259 839 1114 807!1114 807[1013 819 910 802!910 802[706 770 641 611!641 611[755 576 844 578!844 578[908 579 1063
 610!1063 610[1556 707 2046 731!2046 731[2210 769 2238 807"/>
                    <Edge fillStyle1="2" edges="
!1688 1012[1718 992 1760 995!1760 995[1865 1000 1865 1089!1865 1089[1865 1138 1855 1157!1855 1157[1835 1197 1770 1197!1770 1197[1701 1197 1671 1127!1671 1127[#677.3 #429.BA 1655 1074!1655 1074[#677.16 #409.F2 1688 1012"/>
                    <Edge fillStyle0="2" fillStyle1="3" edges="
!1597 1883[1595 1877 1595 1874!1595 1874[1595 1864 1596 1857!1596 1857[1594 1855 1592 1853!1592 1853[1558 1815 1545 1772!1545 1772[1585 1671 1670 1723!1670 1723[1702 1743 1726 1777!1726 1777[1750 1810 1750 1832!1750 1832[1750 1882 1745
 1877!1745 1877|1733 1890!1733 1890[1728 1895 1720 1898!1720 1898[1727 1917 1729 1937"/>
                    <Edge fillStyle0="2" edges="
!1729 1937[1765 1920 1811 1873!1811 1873[1840 1842 1856 1822!1856 1822[1863 1822 1870 1822!1870 1822[1928 1822 1956 1807!1956 1807[1990 1788 1990 1739!1990 1739[1990 1679 1822 1635!1822 1635[1671 1596 1453 1586!1453 1586[1234 1575 1083
 1600!1083 1600[915 1627 915 1687!915 1687[915 1683 921 1717!921 1717[938 1757 990 1757!990 1757[1039 1757 1085 1758!1085 1758[1080 1761 1080 1767!1080 1767[1092 1772 1103 1778!1103 1778[1112 1792 1129 1818"/>
                    <Edge fillStyle0="2" fillStyle1="3" edges="
!1129 1818[1125 1806 1123 1798!1123 1798[1119 1793 1116 1787!1116 1787[1095 1751 1095 1712!1095 1712[1095 1614 1185 1668!1185 1668[1190 1671 1195 1674!1195 1674[1213 1659 1238 1666!1238 1666[1305 1686 1305 1792!1305 1792[1305 1842 1300
 1837!1300 1837|1290 1847!1290 1847[1287 1850 1284 1852!1284 1852[1284 1854 1285 1857!1285 1857|1285 1915"/>
                    <Edge fillStyle0="2" edges="
!1285 1915[1287 1916 1290 1917!1290 1917[1314 1911 1354 1852!1354 1852[1389 1799 1394 1763!1394 1763[1467 1766 1525 1770!1525 1770[1538 1797 1571 1847!1571 1847[1584 1867 1597 1883"/>
                    <Edge fillStyle1="3" edges="
!1729 1937[1730 1945 1730 1954!1730 1954[1730 1982 1702 2006!1702 2006[1673 2026 1670 2027!1670 2027[1651 2003 1622 1945!1622 1945[1601 1901 1597 1883"/>
                    <Edge fillStyle1="2" edges="
!1196 978[1230 1013 1230 1024!1230 1024[1230 1061 1171 1082!1171 1082[1130 1097 1100 1097!1100 1097[1025 1097 1010 1042!1010 1042|1010 997!1010 997[1010 859 1120 920!1120 920[1158 941 1196 978"/>
                    <Edge fillStyle1="3" edges="
!1285 1915|1285 1977!1285 1977[1284 1977 1273 1985!1273 1985[1262 1994 1250 1997!1250 1997[1225 1979 1219 1964!1219 1964[1217 1958 1216 1946!1216 1946[1206 1947 1195 1947!1195 1947[1176 1947 1146 1867!1146 1867[1135 1837 1129 1818"/>
                    <Edge cubics="!1990 1739(;1990,1809 1938,1822 1870,1822q1990 1739Q1990 1788q1956 1807Q1928 1822q1870 1822);"/>
                    <Edge cubics="!915 1687(;915,1517 1990,1569 1990,1739q915 1687Q915 1627q1083 1600Q1234 1575q1453 1586Q1671 1596q1822 1635Q1990 1679q1990 1739);"/>
                    <Edge cubics="!1230 1024(;1230,1082 1115,1097 1100,1097q1230 1024Q1230 1061q1171 1082Q1130 1097q1100 1097);"/>
                    <Edge cubics="!1010 997(;1010,782 1230,997 1230,1024q1010 997Q1010 859q1120 920Q1158 941q1196 978Q1230 1013q1230 1024);"/>
                    <Edge cubics="!1865 1089(;1865,1127 1870,1197 1770,1197q1865 1089Q1865 1138q1855 1157Q1835 1197q1770 1197);"/>
                    <Edge cubics="!1655 1074(;1655,962 1865,969 1865,1089q1655 1074Q1655 1034q1688 1012Q1718 992q1760 995Q1865 1000q1865 1089);"/>
                    <Edge cubics="!1305 1792(;1305,1842 1300,1837 1300,1837q1305 1792Q1305 1842q1300 1837);"/>
                    <Edge cubics="!1750 1832(;1750,1882 1745,1877 1745,1877q1750 1832Q1750 1882q1745 1877);"/>
                    <Edge cubics="!1545 1772(;1605,1619 1750,1774 1750,1832q1545 1772Q1585 1671q1670 1723Q1702 1743q1726 1777Q1750 1810q1750 1832);"/>
                    <Edge cubics="!1285 1857(;1285,1857 1285,1915 1285,1915q1285 1857 1285 1915);"/>
                    <Edge cubics="!1285 1915(;1285,1915 1285,1977 1285,1977q1285 1915 1285 1977);"/>
                    <Edge cubics="!1285 1977(;1280,1977 1270,1992 1250,1997q1285 1977Q1284 1977q1273 1985Q1262 1994q1250 1997);"/>
                    <Edge cubics="!1730 1954(;1730,1999 1675,2024 1670,2027q1730 1954Q1730 1982q1702 2006Q1673 2026q1670 2027);"/>
                    <Edge cubics="!1770 1197(;1724,1197 1691,1174 1671,1127q1770 1197Q1701 1197q1671 1127);"/>
                    <Edge cubics="!1100 1097(;1050,1097 1020,1079 1010,1042q1100 1097Q1025 1097q1010 1042);"/>
                    <Edge cubics="!1010 1042(;1010,1042 1010,997 1010,997q1010 1042 1010 997);"/>
                    <Edge cubics="!1103 1778(;1096,1774 1088,1770 1080,1767q1103 1778Q1092 1772q1080 1767);"/>
                    <Edge cubics="!1080 1767(;1080,1763 1082,1760 1085,1758q1080 1767Q1080 1761q1085 1758);"/>
                    <Edge cubics="!990 1757(;955,1757 932,1744 921,1717q990 1757Q938 1757q921 1717);"/>
                    <Edge cubics="!1129 1818(;1126,1810 1124,1803 1123,1798q1129 1818Q1125 1806q1123 1798);"/>
                    <Edge cubics="!1123 1798(;1120,1795 1118,1791 1116,1787q1123 1798Q1119 1793q1116 1787);"/>
                    <Edge cubics="!1146 1867(;1139,1847 1133,1831 1129,1818q1146 1867Q1135 1837q1129 1818);"/>
                    <Edge cubics="!1129 1818(;1118,1801 1109,1787 1103,1778q1129 1818Q1112 1792q1103 1778);"/>
                    <Edge cubics="!1116 1787(;1102,1763 1095,1738 1095,1712q1116 1787Q1095 1751q1095 1712);"/>
                    <Edge cubics="!1185 1668(;1188,1670 1192,1672 1195,1674q1185 1668Q1190 1671q1195 1674);"/>
                    <Edge cubics="!1195 1674(;1207,1664 1221,1661 1238,1666q1195 1674Q1213 1659q1238 1666);"/>
                    <Edge cubics="!1525 1770(;1486,1767 1443,1765 1394,1763q1525 1770Q1467 1766q1394 1763);"/>
                    <Edge cubics="!1300 1837(;1300,1837 1290,1847 1290,1847q1300 1837 1290 1847);"/>
                    <Edge cubics="!1216 1946(;1209,1947 1202,1947 1195,1947q1216 1946Q1206 1947q1195 1947);"/>
                    <Edge cubics="!1219 1964(;1218,1960 1217,1954 1216,1946q1219 1964Q1217 1958q1216 1946);"/>
                    <Edge cubics="!1250 1997(;1233,1985 1223,1974 1219,1964q1250 1997Q1225 1979q1219 1964);"/>
                    <Edge cubics="!1290 1917(;1288,1916 1286,1916 1285,1915q1290 1917Q1287 1916q1285 1915);"/>
                    <Edge cubics="!1284 1852(;1284,1853 1284,1855 1285,1857q1284 1852Q1284 1854q1285 1857);"/>
                    <Edge cubics="!1290 1847(;1288,1849 1286,1851 1284,1852q1290 1847Q1287 1850q1284 1852);"/>
                    <Edge cubics="!1354 1852(;1327,1891 1306,1913 1290,1917q1354 1852Q1314 1911q1290 1917);"/>
                    <Edge cubics="!1870 1822(;1865,1822 1861,1822 1856,1822q1870 1822Q1863 1822q1856 1822);"/>
                    <Edge cubics="!1856 1822(;1845,1835 1830,1852 1811,1873q1856 1822Q1840 1842q1811 1873);"/>
                    <Edge cubics="!1733 1890(;1730,1893 1725,1896 1720,1898q1733 1890Q1728 1895q1720 1898);"/>
                    <Edge cubics="!1745 1877(;1745,1877 1733,1890 1733,1890q1745 1877 1733 1890);"/>
                    <Edge cubics="!1597 1883(;1596,1879 1595,1876 1595,1874q1597 1883Q1595 1877q1595 1874);"/>
                    <Edge cubics="!1595 1874(;1595,1867 1595,1862 1596,1857q1595 1874Q1595 1864q1596 1857);"/>
                    <Edge cubics="!1596 1857(;1595,1856 1593,1854 1592,1853q1596 1857Q1594 1855q1592 1853);"/>
                    <Edge cubics="!1670 2027(;1657,2011 1641,1984 1622,1945q1670 2027Q1651 2003q1622 1945);"/>
                    <Edge cubics="!1729 1937(;1730,1942 1730,1948 1730,1954q1729 1937Q1730 1945q1730 1954);"/>
                    <Edge cubics="!1622 1945(;1608,1916 1600,1895 1597,1883q1622 1945Q1601 1901q1597 1883);"/>
                    <Edge cubics="!1720 1898(;1725,1911 1728,1924 1729,1937q1720 1898Q1727 1917q1729 1937);"/>
                    <Edge cubics="!1811 1873(;1780,1904 1753,1926 1729,1937q1811 1873Q1765 1920q1729 1937);"/>
                    <Edge cubics="!1597 1883(;1588,1872 1580,1860 1571,1847q1597 1883Q1584 1867q1571 1847);"/>
                    <Edge cubics="!1592 1853(;1569,1828 1554,1801 1545,1772q1592 1853Q1558 1815q1545 1772);"/>
                    <Edge cubics="!1238 1666(;1283,1679 1305,1721 1305,1792q1238 1666Q1305 1686q1305 1792);"/>
                    <Edge cubics="!1571 1847(;1549,1814 1534,1788 1525,1770q1571 1847Q1538 1797q1525 1770);"/>
                    <Edge cubics="!1394 1763(;1391,1787 1377,1817 1354,1852q1394 1763Q1389 1799q1354 1852);"/>
                    <Edge cubics="!1195 1947(;1182,1947 1166,1920 1146,1867q1195 1947Q1176 1947q1146 1867);"/>
                    <Edge cubics="!1095 1712(;1095,1647 1125,1632 1185,1668q1095 1712Q1095 1614q1185 1668);"/>
                    <Edge cubics="!2265 869(;2274,918 2273,1002 2197,1002q2265 869Q2274 918q2263 954Q2247 1002q2197 1002);"/>
                    <Edge cubics="!2197 1002(;1360,1002 1405,869 1114,807q2197 1002Q1686 1002q1451 928Q1259 839q1114 807);"/>
                    <Edge cubics="!1114 807(;1096,802 745,865 641,611q1114 807Q1013 819q910 802Q706 770q641 611);"/>
                    <Edge cubics="!2238 807(;2251,822 2260,843 2265,869q2238 807Q2257 830q2265 869);"/>
                    <Edge cubics="!2046 731(;2155,756 2219,782 2238,807q2046 731Q2210 769q2238 807);"/>
                    <Edge cubics="!641 611(;718,588 785,577 844,578q641 611Q755 576q844 578);"/>
                    <Edge cubics="!844 578(;887,579 960,589 1063,610q844 578Q908 579q1063 610);"/>
                    <Edge cubics="!1063 610(;1392,675 1720,715 2046,731q1063 610Q1556 707q2046 731);"/>
                    <Edge cubics="!1085 1758(;1054,1757 1023,1757 990,1757q1085 1758Q1039 1757q990 1757);"/>
                    <Edge cubics="!921 1717(;917,1694 915,1684 915,1687q921 1717Q915 1683q915 1687);"/>
                    <Edge cubics="!1671 1127(;1660,1086 1655,1069 1655,1074q1671 1127Q1655 1066q1655 1074);"/>
                  </edges>
                </DOMShape>
              </elements>
            </DOMFrame>
          </frames>
        </DOMLayer>
        <DOMLayer name="Layer 2" color="#9933CC" current="true" isSelected="true">
          <frames>
            <DOMFrame index="0" keyMode="9728">
              <elements>
                <DOMGroup>
                  <transformationPoint>
                    <Point x="77.2" y="75.75"/>
                  </transformationPoint>
                  <members>
                    <DOMShape>
                      <transformationPoint>
                        <Point x="77.2" y="75.75"/>
                      </transformationPoint>
                      <fills>
                        <FillStyle index="1">
                          <SolidColor color="#A9721C" alpha="0.976470588235294"/>
                        </FillStyle>
                        <FillStyle index="2">
                          <SolidColor color="#9C6818" alpha="0.976470588235294"/>
                        </FillStyle>
                        <FillStyle index="3">
                          <SolidColor color="#9E6712" alpha="0.976470588235294"/>
                        </FillStyle>
                        <FillStyle index="4">
                          <SolidColor color="#3C175E" alpha="0.976470588235294"/>
                        </FillStyle>
                      </fills>
                      <edges>
                        <Edge fillStyle1="1" edges="
!2210 226S2[2366 194 2592 393!2592 393[2752 536 2874 712!2874 712[2915 770 2904 915"/>
                        <Edge fillStyle1="3" edges="
!2904 915S2[2924 961 2945 1014!2945 1014[3040 1269 3057 1517!3057 1517[3070 1719 3033 1896"/>
                        <Edge fillStyle1="1" edges="
!3033 1896S2[3056 1963 3074 1989!3074 1989[3137 2080 3119 2154!3119 2154[3089 2277 2857 2438!2857 2438[2744 2516 2671 2519"/>
                        <Edge fillStyle1="3" edges="
!2671 2519S2[2586 2598 2483 2669!2483 2669[2153 2898 1835 2976"/>
                        <Edge fillStyle1="1" edges="
!1835 2976S2[1638 3088 1460 3062!1460 3062[1340 3047 1286 2995"/>
                        <Edge fillStyle1="3" edges="
!1286 2995S2[1126 2965 973 2894!973 2894[813 2823 678 2724"/>
                        <Edge fillStyle1="1" edges="
!678 2724S2[487 2713 454 2666!454 2666[416 2611 413 2478"/>
                        <Edge fillStyle1="3" edges="
!413 2478S2[356 2411 305 2337!305 2337[204 2192 130 1993!130 1993[39 1753 24 1518!24 1518[11 1332 47 1168"/>
                        <Edge fillStyle1="1" edges="
!47 1168S2[2 1095 0 1037!0 1037[-3 909 157 798!157 798[190 775 224 760"/>
                        <Edge fillStyle1="3" edges="
!224 760S2[321 624 465 509!465 509[598 390 733 299"/>
                        <Edge fillStyle1="1" edges="
!733 299S2[752 254 785 219!785 219[876 123 1112 68!1112 68[1615 -33 1715 17!1715 17[1744 31 1770 68"/>
                        <Edge fillStyle1="3" edges="
!1770 68S2[1893 91 2016 137!2016 137[2115 175 2210 226"/>
                        <Edge fillStyle0="1" fillStyle1="2" edges="
!2544 651S3|2564 700!2564 700[2562 708 2557 716!2557 716[2548 734 2531 751!2531 751[2511 746 2430 684!2430 684[2356 627 2351 618!2351 618[2331 591 2336 586!2336 586[2340 583 2348 576!2348 576[2413 555 2472 596!2472 596[2503 618 2544 651"/>
                        <Edge fillStyle0="3" fillStyle1="1" edges="
!1770 68S3[1782 86 1794 108!1794 108[1850 223 1878 264!1878 264[1903 300 1957 332!1957 332[1970 340 2059 386!2059 386[2057 367 2080 323!2080 323[2106 277 2130 261!2130 261[2167 235 2210 226!1690 280[1711 310 1708 339!1708 339[1734 346
 1759 353!1759 353[1737 323 1714 290!1714 290[1656 200 1655 199!1655 199[1643 182 1608 177!1608 177[1607 181 1606 187!1606 187[1597 234 1601 239!1601 239[1617 263 1646 260!1646 260[1674 257 1690 280"/>
                        <Edge fillStyle0="1" fillStyle1="4" edges="
!1834 756S3[1805 753 1800 753!1800 753[1782 748 1773 735!1773 735[1726 667 1775 603!1775 603[1824 542 1885 629!1885 629[1912 669 1880 747"/>
                        <Edge fillStyle0="1" fillStyle1="2" edges="
!1880 747S3[1903 752 1913 760!1913 760[1919 777 1901 802!1901 802[1872 814 1848 804!1848 804[1830 797 1820 783!1820 783[1823 768 1834 756"/>
                        <Edge fillStyle0="2" fillStyle1="4" edges="
!1880 747S3[1877 754 1873 760!1873 760[1850 758 1834 756"/>
                        <Edge fillStyle0="1" fillStyle1="4" edges="
!2385 659S3[2384 712 2361 752!2361 752[2295 745 2288 744!2288 744[2269 740 2260 726!2260 726[2217 664 2264 630!2264 630[2312 595 2385 659"/>
                        <Edge fillStyle0="3" fillStyle1="1" edges="
!2225 615S3[2221 617 2217 618!2217 618[2229 628 2241 639!2241 639[2234 628 2227 618!2227 618[2225 616 2225 615"/>
                        <Edge fillStyle0="1" fillStyle1="2" edges="
!2215 912S3[2228 917 2246 944!2246 944[2284 997 2219 1042!2219 1042[2194 1059 2144 1084!2144 1084[2095 1108 2080 1119!2080 1119[2079 1047 2102 991!2102 991[2134 915 2199 905!2199 905[2201 907 2215 912!1633 1304|1585 1256!1585 1256[1575
 1139 1643 1124!1643 1124[1703 1108 1735 1154!1735 1154[1753 1180 1751 1216!1751 1216[1748 1259 1713 1282!1713 1282[1685 1302 1671 1303!1671 1303[1651 1303 1633 1304"/>
                        <Edge fillStyle0="1" fillStyle1="4" edges="
!2138 1750S3[2156 1762 2175 1789!2175 1789[2184 1802 2178 1855!2178 1855[2173 1904 2163 1931!2163 1931[2104 1926 2091 1924!2091 1924[2074 1921 2063 1905!2063 1905[2046 1881 2050 1845!2050 1845[2055 1789 2118 1737!2118 1737[2120 1740 2138
 1750"/>
                        <Edge fillStyle0="1" fillStyle1="3" edges="
!2852 1258S3[2858 1181 2880 1073!2880 1073[2898 984 2904 915"/>
                        <Edge fillStyle0="3" fillStyle1="4" edges="
!2852 1258S3[2876 1265 2905 1276!2905 1276[2951 1297 2954 1301!2954 1301[2970 1324 2963 1358!2963 1358[2955 1400 2914 1432!2914 1432[2888 1428 2865 1417"/>
                        <Edge fillStyle0="3" fillStyle1="1" edges="
!2865 1417S3[2865 1420 2867 1423!2867 1423[2914 1497 2978 1719!2978 1719[3008 1828 3033 1896"/>
                        <Edge fillStyle0="1" fillStyle1="2" edges="
!2625 1407S3[2628 1430 2598 1451!2598 1451[2560 1477 2524 1460!2524 1460[2500 1449 2488 1432!2488 1432[2470 1405 2471 1404!2471 1404[2475 1397 2473 1388!2473 1388[2568 1322 2613 1373!2613 1373[2616 1382 2625 1407"/>
                        <Edge fillStyle0="1" fillStyle1="4" edges="
!2865 1417S3[2847 1410 2831 1402!2831 1402|2804 1381!2804 1381[2702 1234 2816 1251!2816 1251[2832 1253 2852 1258!2483 2025[2483 2022 2484 2019!2484 2019[2491 1914 2561 1862!2561 1862[2563 1865 2576 1868!2576 1868[2589 1873 2607 1900!2607
 1900[2636 1942 2625 2024!2625 2024[2620 2062 2593 2155!2593 2155[2569 2153 2554 2152"/>
                        <Edge fillStyle0="1" fillStyle1="2" edges="
!2554 2152S3[2534 2200 2522 2211!2522 2211[2472 2210 2455 2206!2455 2206[2426 2203 2416 2188!2416 2188[2393 2154 2425 2092!2425 2092[2446 2051 2483 2025"/>
                        <Edge fillStyle0="3" fillStyle1="1" edges="
!2814 1765S3[2814 1772 2814 1781!2814 1781[2818 1781 2821 1782!2821 1782[2817 1773 2814 1765!2843 1688[2851 1746 2853 1748!2853 1748[2860 1758 2871 1768!2871 1768[2864 1731 2843 1688"/>
                        <Edge fillStyle0="1" fillStyle1="2" edges="
!1273 409S3[1268 412 1263 427!1263 427[1257 443 1249 453!1249 453[1216 461 1214 461!1214 461[1197 459 1175 428!1175 428[1154 397 1157 374!1157 374[1157 359 1172 342!1172 342[1205 344 1229 361!1229 361[1249 373 1273 409"/>
                        <Edge fillStyle0="3" fillStyle1="1" edges="
!980 455S3[950 451 926 448!926 448[928 466 932 483!932 483[956 468 980 455"/>
                        <Edge fillStyle0="1" fillStyle1="2" edges="
!1156 882S3[1185 871 1229 870!1229 870|1257 892!1257 892[1266 912 1268 921!1268 921[1270 938 1242 958!1242 958[1213 978 1185 978!1185 978[1157 974 1142 972!1142 972|1123 954!1123 954|1104 917!1104 917[1130 893 1156 882"/>
                        <Edge fillStyle0="3" fillStyle1="1" edges="
!715 558S3[717 501 712 412!712 412[713 349 733 299!314 915[295 928 281 940!281 940[302 941 329 945!329 945[368 950 413 959!413 959[381 936 365 926!365 926[331 903 314 915"/>
                        <Edge fillStyle0="1" fillStyle1="4" edges="
!715 558S3[727 570 738 587!738 587[761 619 764 674!764 674[767 732 741 750!741 750[668 801 614 783"/>
                        <Edge fillStyle0="1" fillStyle1="3" edges="
!614 783S3[608 787 604 790!604 790[571 812 527 796!527 796[470 770 435 756!435 756[332 712 224 760"/>
                        <Edge fillStyle0="3" fillStyle1="4" edges="
!614 783S3[587 774 571 751!571 751[558 734 566 681!566 681[573 626 595 583!595 583[646 482 715 558"/>
                        <Edge fillStyle0="1" fillStyle1="2" edges="
!681 792S3[670 818 624 810!624 810[617 780 681 792!769 1185[766 1226 731 1251!731 1251[702 1271 688 1271!688 1271[669 1270 650 1272!650 1272|603 1223!603 1223[594 1108 660 1090!660 1090[719 1074 752 1122!752 1122[771 1149 769 1185"/>
                        <Edge fillStyle0="3" fillStyle1="1" edges="
!459 1234S3|473 1244!473 1244[479 1225 483 1198!483 1198|490 1150!490 1150[478 1151 472 1163!472 1163[466 1179 464 1199!464 1199|459 1234"/>
                        <Edge fillStyle0="1" fillStyle1="4" edges="
!678 1481S3[700 1512 702 1598!702 1598[704 1677 693 1709!693 1709[643 1715 606 1683!606 1683[590 1669 563 1630!563 1630[501 1541 562 1472!562 1472[586 1443 618 1443!618 1443[653 1444 678 1481"/>
                        <Edge fillStyle0="3" fillStyle1="1" edges="
!413 2478S3[413 2455 413 2429!413 2429[415 2258 353 2170!353 2170[234 1998 304 1824!304 1824[288 1770 275 1717!275 1717[239 1579 226 1466!226 1466|69 1205!69 1205[56 1186 47 1168!258 1133[252 1131 247 1128!247 1128[252 1133 258 1137!258
 1137[258 1135 258 1133"/>
                        <Edge fillStyle0="1" fillStyle1="2" edges="
!433 1988S3[389 1963 376 1945!376 1945[364 1927 383 1886!383 1886[403 1845 392 1829!392 1829[451 1814 507 1859!507 1859[539 1886 606 1940!606 1940[609 1950 620 1966!620 1966[623 1983 594 2003!594 2003[588 2008 582 2010!582 2010[630 2042
 673 2086!673 2086[675 2100 672 2106!672 2106[666 2119 635 2140!635 2140[601 2163 534 2114!534 2114[523 2103 513 2094"/>
                        <Edge fillStyle0="1" fillStyle1="4" edges="
!513 2094S3[509 2123 500 2144!500 2144[448 2137 433 2132!433 2132[413 2127 408 2121!408 2121[378 2077 395 2033!395 2033[405 2004 433 1988"/>
                        <Edge fillStyle0="1" fillStyle1="2" edges="
!764 1697S3|768 1698!768 1698[783 1681 798 1669!798 1669[823 1650 874 1624!874 1624[879 1632 898 1649!898 1649[917 1667 921 1674!921 1674[923 1715 906 1740!906 1740|828 1766!828 1766|815 1762!815 1762[803 1759 783 1731!783 1731[763 1702
 764 1697"/>
                        <Edge fillStyle0="2" fillStyle1="4" edges="
!433 1988S3[448 1978 471 1973!471 1973[473 1975 481 1978!481 1978[490 1981 509 2008!509 2008[515 2017 515 2062!515 2062[513 2078 513 2094"/>
                        <Edge fillStyle0="3" fillStyle1="1" edges="
!979 1354S3[987 1305 1003 1252!1003 1252[977 1295 959 1353!959 1353[969 1352 979 1354!1029 1660[1025 1655 1023 1650!1023 1650[984 1632 949 1614!949 1614|952 1619!952 1619|981 1680!981 1680[1027 1706 1068 1729!1068 1729[1049 1694 1029
 1660"/>
                        <Edge fillStyle0="1" fillStyle1="4" edges="
!1595 1625S3[1613 1650 1612 1707!1612 1707[1606 1773 1604 1798!1604 1798[1545 1792 1532 1790!1532 1790[1515 1787 1504 1771!1504 1771[1472 1725 1495 1619!1495 1619[1518 1514 1595 1625"/>
                        <Edge fillStyle0="1" fillStyle1="2" edges="
!1615 2419S3[1635 2416 1655 2444!1655 2444[1688 2492 1650 2575!1650 2575[1609 2586 1609 2587!1609 2587[1589 2587 1568 2557!1568 2557[1564 2551 1566 2508!1566 2508[1568 2459 1578 2433!1578 2433[1593 2429 1615 2419!1221 2375[1208 2398 1203
 2405!1203 2405[1127 2385 1120 2376!1120 2376[1100 2347 1124 2318!1124 2318[1146 2293 1183 2288!1183 2288|1221 2303!1221 2303|1240 2352!1240 2352[1233 2357 1221 2375"/>
                        <Edge fillStyle0="3" fillStyle1="1" edges="
!854 2538S3[772 2494 692 2446!692 2446[663 2426 637 2409!637 2409[634 2470 609 2529!609 2529[718 2555 844 2539!844 2539[848 2539 854 2538!1212 2683[1207 2682 1204 2681!1204 2681[1007 2728 756 2726!756 2726[714 2725 678 2724"/>
                        <Edge fillStyle0="3" fillStyle1="4" edges="
!1229 2787S3[1220 2777 1211 2765!1211 2765[1187 2729 1207 2693!1207 2693[1210 2689 1212 2683"/>
                        <Edge fillStyle0="1" fillStyle1="4" edges="
!1212 2683S3[1230 2656 1269 2640!1269 2640[1380 2592 1442 2681!1442 2681[1463 2712 1463 2739!1463 2739[1461 2767 1437 2784!1437 2784[1359 2838 1294 2821!1294 2821[1256 2813 1229 2787"/>
                        <Edge fillStyle0="1" fillStyle1="3" edges="
!1229 2787S3[1231 2820 1232 2855!1232 2855[1230 2920 1266 2971!1266 2971[1274 2984 1286 2995"/>
                        <Edge fillStyle0="3" fillStyle1="1" edges="
!2669 2184S3[2673 2198 2675 2222!2675 2222[2679 2280 2695 2303!2695 2303|2703 2305!2703 2305[2717 2301 2746 2281!2746 2281[2771 2264 2783 2235!2783 2235[2782 2236 2781 2235!2781 2235[2722 2201 2691 2158!2691 2158[2688 2156 2687 2155!2687
 2155[2686 2159 2684 2164!2684 2164[2680 2173 2669 2184"/>
                        <Edge fillStyle0="2" fillStyle1="4" edges="
!2554 2152S3[2529 2150 2520 2148!2520 2148[2504 2146 2501 2142!2501 2142[2477 2107 2483 2025"/>
                        <Edge fillStyle0="3" fillStyle1="1" edges="
!2671 2519S3[2626 2521 2594 2497!2594 2497[2569 2475 2549 2432!2549 2432[2534 2388 2527 2378!2527 2378[2418 2449 2340 2482!2340 2482[2287 2531 2225 2574!2225 2574[2143 2631 2053 2670!2053 2670[2052 2671 2052 2673!2052 2673[2014 2858 1918
 2924!1918 2924[1877 2953 1835 2976"/>
                        <Edge fillStyle0="1" fillStyle1="4" edges="
!2032 2497S3[2022 2493 2014 2488!2014 2488[2011 2447 2033 2390!2033 2390[2061 2321 2111 2282!2111 2282[2113 2285 2128 2289!2128 2289[2140 2294 2159 2321!2159 2321[2179 2351 2189 2393!2189 2393[2204 2459 2164 2486!2164 2486[2148 2497 2127
 2503"/>
                        <Edge fillStyle0="1" fillStyle1="2" edges="
!2127 2503S3[2128 2504 2129 2505!2129 2505[2151 2537 2103 2596!2103 2596[2065 2643 2010 2681!2010 2681[1982 2701 1971 2702!1971 2702|1967 2698!1967 2698[1952 2700 1947 2700!1947 2700[1940 2697 1920 2668!1920 2668[1903 2644 1927 2597!1927
 2597[1952 2542 2032 2497!2001 2094[2034 2141 2021 2132!2021 2132|2014 2155!2014 2155[2005 2178 1977 2198!1977 2198[1917 2239 1854 2187!1854 2187[1809 2132 1814 2140!1814 2140[1744 2038 1852 2037!1852 2037[1962 2037 2001 2094"/>
                        <Edge fillStyle0="2" fillStyle1="4" edges="
!2127 2503S3[2106 2507 2080 2506!2080 2506[2051 2504 2032 2497"/>
                        <Edge cubics="!472 1163(;463,1190 463,1210 459,1234q472 1163Q466 1179q464 1199Q459 1234q459 1234);"/>
                        <Edge cubics="!459 1234(;459,1234 473,1244 473,1244q459 1234 473 1244);"/>
                        <Edge cubics="!473 1244(;483,1213 485,1181 490,1150q473 1244Q479 1225q483 1198Q490 1150q490 1150);"/>
                        <Edge cubics="!490 1150(;490,1150 478,1151 472,1163q490 1150Q478 1151q472 1163);"/>
                        <Edge cubics="!952 1619(;952,1619 981,1680 981,1680q952 1619 981 1680);"/>
                        <Edge cubics="!949 1614(;949,1614 952,1619 952,1619q949 1614 952 1619);"/>
                        <Edge cubics="!1878 264(;1917,319 1990,350 2059,386q1878 264Q1903 300q1957 332Q1970 340q2059 386);"/>
                        <Edge cubics="!2059 386(;2056,362 2096,285 2130,261q2059 386Q2057 367q2080 323Q2106 277q2130 261);"/>
                        <Edge cubics="!3074 1989(;3132,2072 3209,2194 2857,2438q3074 1989Q3137 2080q3119 2154Q3089 2277q2857 2438);"/>
                        <Edge cubics="!2695 2303(;2695,2303 2700,2313 2746,2281q2695 2303Q2695 2303q2703 2305Q2717 2301q2746 2281);"/>
                        <Edge cubics="!1601 239(;1633,286 1658,234 1690,280q1601 239Q1617 263q1646 260Q1674 257q1690 280);"/>
                        <Edge cubics="!673 2086(;674,2099 681,2108 635,2140q673 2086Q675 2100q672 2106Q666 2119q635 2140);"/>
                        <Edge cubics="!392 1829(;490,1804 529,1898 606,1940q392 1829Q451 1814q507 1859Q539 1886q606 1940);"/>
                        <Edge cubics="!606 1940(;611,1958 640,1971 594,2003q606 1940Q609 1950q620 1966Q623 1983q594 2003);"/>
                        <Edge cubics="!376 1945(;352,1910 414,1862 392,1829q376 1945Q364 1927q383 1886Q403 1845q392 1829);"/>
                        <Edge cubics="!874 1624(;883,1638 912,1660 921,1674q874 1624Q879 1632q898 1649Q917 1667q921 1674);"/>
                        <Edge cubics="!921 1674(;922,1694 923,1715 906,1740q921 1674Q923 1715q906 1740);"/>
                        <Edge cubics="!906 1740(;906,1740 828,1766 828,1766q906 1740 828 1766);"/>
                        <Edge cubics="!828 1766(;822,1757 815,1777 783,1731q828 1766Q828 1766q815 1762Q803 1759q783 1731);"/>
                        <Edge cubics="!783 1731(;751,1685 768,1698 768,1698q783 1731Q763 1702q764 1697Q768 1698q768 1698);"/>
                        <Edge cubics="!768 1698(;783,1681 798,1664 874,1624q768 1698Q783 1681q798 1669Q823 1650q874 1624);"/>
                        <Edge cubics="!1183 2288(;1183,2288 1221,2303 1221,2303q1183 2288p1221 2303);"/>
                        <Edge cubics="!1221 2303(;1221,2303 1240,2352 1240,2352q1221 2303p1240 2352);"/>
                        <Edge cubics="!1240 2352(;1227,2361 1218,2388 1203,2405q1240 2352Q1233 2357q1221 2375Q1208 2398q1203 2405);"/>
                        <Edge cubics="!1203 2405(;1174,2398 1127,2385 1120,2376q1203 2405Q1127 2385q1120 2376);"/>
                        <Edge cubics="!1120 2376(;1091,2334 1139,2293 1183,2288q1120 2376Q1100 2347q1124 2318Q1146 2293q1183 2288);"/>
                        <Edge cubics="!2001 2094(;2034,2141 2021,2132 2021,2132q2001 2094Q2034 2141q2021 2132);"/>
                        <Edge cubics="!2021 2132(;2012,2138 2024,2166 1977,2198q2021 2132Q2021 2132q2014 2155Q2005 2178q1977 2198);"/>
                        <Edge cubics="!1578 2433(;1608,2426 1623,2398 1655,2444q1578 2433Q1593 2429q1615 2419Q1635 2416q1655 2444);"/>
                        <Edge cubics="!1655 2444(;1682,2484 1670,2529 1650,2575q1655 2444Q1688 2492q1650 2575);"/>
                        <Edge cubics="!1650 2575(;1615,2585 1600,2603 1568,2557q1650 2575Q1609 2586q1609 2587Q1589 2587q1568 2557);"/>
                        <Edge cubics="!1568 2557(;1565,2552 1563,2474 1578,2433q1568 2557Q1564 2551q1566 2508Q1568 2459q1578 2433);"/>
                        <Edge cubics="!2129 2505(;2162,2553 2066,2642 2010,2681q2129 2505Q2151 2537q2103 2596Q2065 2643q2010 2681);"/>
                        <Edge cubics="!2010 2681(;1964,2713 1967,2698 1967,2698q2010 2681Q1982 2701q1971 2702Q1967 2698q1967 2698);"/>
                        <Edge cubics="!1967 2698(;1943,2693 1952,2715 1920,2668q1967 2698Q1952 2700q1947 2700Q1940 2697q1920 2668);"/>
                        <Edge cubics="!2522 2211(;2468,2207 2432,2211 2416,2188q2522 2211Q2472 2210q2455 2206Q2426 2203q2416 2188);"/>
                        <Edge cubics="!2613 1373(;2618,1390 2645,1419 2598,1451q2613 1373Q2616 1382q2625 1407Q2628 1430q2598 1451);"/>
                        <Edge cubics="!2598 1451(;2538,1492 2493,1438 2488,1432q2598 1451Q2560 1477q2524 1460Q2500 1449q2488 1432);"/>
                        <Edge cubics="!2488 1432(;2456,1385 2479,1418 2473,1388q2488 1432Q2470 1405q2471 1404Q2475 1397q2473 1388);"/>
                        <Edge cubics="!2473 1388(;2503,1367 2569,1323 2613,1373q2473 1388Q2568 1322q2613 1373);"/>
                        <Edge cubics="!2199 905(;2209,918 2214,897 2246,944q2199 905Q2201 907q2215 912Q2228 917q2246 944);"/>
                        <Edge cubics="!2246 944(;2280,993 2245,1024 2219,1042q2246 944Q2284 997q2219 1042);"/>
                        <Edge cubics="!2219 1042(;2173,1074 2112,1096 2080,1119q2219 1042Q2194 1059q2144 1084Q2095 1108q2080 1119);"/>
                        <Edge cubics="!2080 1119(;2078,1046 2101,921 2199,905q2080 1119Q2079 1047q2102 991Q2134 915q2199 905);"/>
                        <Edge cubics="!1735 1154(;1754,1182 1764,1247 1713,1282q1735 1154Q1753 1180q1751 1216Q1748 1259q1713 1282);"/>
                        <Edge cubics="!1713 1282(;1667,1314 1670,1299 1633,1304q1713 1282Q1685 1302q1671 1303Q1651 1303q1633 1304);"/>
                        <Edge cubics="!1633 1304(;1633,1304 1585,1256 1585,1256q1633 1304 1585 1256);"/>
                        <Edge cubics="!1585 1256(;1571,1081 1705,1111 1735,1154q1585 1256Q1575 1139q1643 1124Q1703 1108q1735 1154);"/>
                        <Edge cubics="!752 1122(;773,1152 782,1215 731,1251q752 1122Q771 1149q769 1185Q766 1226q731 1251);"/>
                        <Edge cubics="!731 1251(;685,1283 688,1266 650,1272q731 1251Q702 1271q688 1271Q669 1270q650 1272);"/>
                        <Edge cubics="!650 1272(;650,1272 603,1223 603,1223q650 1272 603 1223);"/>
                        <Edge cubics="!603 1223(;589,1050 720,1075 752,1122q603 1223Q594 1108q660 1090Q719 1074q752 1122);"/>
                        <Edge cubics="!681 792(;674,810 648,814 624,810q681 792Q670 818q624 810);"/>
                        <Edge cubics="!624 810(;620,792 634,783 681,792q624 810Q617 780q681 792);"/>
                        <Edge cubics="!1172 342(;1220,342 1244,367 1273,409q1172 342Q1205 344q1229 361Q1249 373q1273 409);"/>
                        <Edge cubics="!1273 409(;1263,416 1264,435 1249,453q1273 409Q1268 412q1263 427Q1257 443q1249 453);"/>
                        <Edge cubics="!1249 453(;1218,460 1208,474 1175,428q1249 453Q1216 461q1214 461Q1197 459q1175 428);"/>
                        <Edge cubics="!1175 428(;1143,382 1156,360 1172,342q1175 428Q1154 397q1157 374Q1157 359q1172 342);"/>
                        <Edge cubics="!1229 870(;1229,870 1257,892 1257,892q1229 870 1257 892);"/>
                        <Edge cubics="!1257 892(;1258,912 1288,926 1242,958q1257 892Q1266 912q1268 921Q1270 938q1242 958);"/>
                        <Edge cubics="!1242 958(;1195,990 1170,973 1142,972q1242 958Q1213 978q1185 978Q1157 974q1142 972);"/>
                        <Edge cubics="!1142 972(;1142,972 1123,954 1123,954q1142 972 1123 954);"/>
                        <Edge cubics="!1123 954(;1123,954 1104,917 1104,917q1123 954 1104 917);"/>
                        <Edge cubics="!1104 917(;1138,887 1168,872 1229,870q1104 917Q1130 893q1156 882Q1185 871q1229 870);"/>
                        <Edge cubics="!1913 760(;1913,760 1919,777 1901,802q1913 760Q1919 777q1901 802);"/>
                        <Edge cubics="!1901 802(;1858,819 1830,797 1820,783q1901 802Q1872 814q1848 804Q1830 797q1820 783);"/>
                        <Edge cubics="!2544 651(;2544,651 2564,700 2564,700q2544 651 2564 700);"/>
                        <Edge cubics="!2564 700(;2560,703 2560,723 2531,751q2564 700Q2562 708q2557 716Q2548 734q2531 751);"/>
                        <Edge cubics="!2531 751(;2499,745 2354,623 2351,618q2531 751Q2511 746q2430 684Q2356 627q2351 618);"/>
                        <Edge cubics="!2351 618(;2318,572 2345,591 2348,576q2351 618Q2331 591q2336 586Q2340 583q2348 576);"/>
                        <Edge cubics="!2348 576(;2453,543 2507,636 2544,651q2348 576Q2413 555q2472 596Q2503 618q2544 651);"/>
                        <Edge cubics="!1442 2681(;1470,2722 1469,2761 1437,2784q1442 2681Q1463 2712q1463 2739Q1461 2767q1437 2784);"/>
                        <Edge cubics="!678 1481(;709,1526 706,1673 693,1709q678 1481Q700 1512q702 1598Q704 1677q693 1709);"/>
                        <Edge cubics="!693 1709(;615,1717 582,1658 563,1630q693 1709Q643 1715q606 1683Q590 1669q563 1630);"/>
                        <Edge cubics="!563 1630(;478,1508 607,1377 678,1481q563 1630Q501 1541q562 1472Q586 1443q618 1443Q653 1444q678 1481);"/>
                        <Edge cubics="!738 587(;765,626 778,724 741,750q738 587Q761 619q764 674Q767 732q741 750);"/>
                        <Edge cubics="!471 1973(;481,1986 477,1962 509,2008q471 1973Q473 1975q481 1978Q490 1981q509 2008);"/>
                        <Edge cubics="!500 2144(;436,2134 415,2130 408,2121q500 2144Q448 2137q433 2132Q413 2127q408 2121);"/>
                        <Edge cubics="!2118 1737(;2127,1751 2143,1743 2175,1789q2118 1737Q2120 1740q2138 1750Q2156 1762q2175 1789);"/>
                        <Edge cubics="!2175 1789(;2188,1808 2175,1898 2163,1931q2175 1789Q2184 1802q2178 1855Q2173 1904q2163 1931);"/>
                        <Edge cubics="!2163 1931(;2089,1923 2079,1928 2063,1905q2163 1931Q2104 1926q2091 1924Q2074 1921q2063 1905);"/>
                        <Edge cubics="!2063 1905(;2051,1888 2020,1818 2118,1737q2063 1905Q2046 1881q2050 1845Q2055 1789q2118 1737);"/>
                        <Edge cubics="!2954 1301(;2970,1324 2975,1385 2914,1432q2954 1301Q2970 1324q2963 1358Q2955 1400q2914 1432);"/>
                        <Edge cubics="!2385 659(;2385,702 2378,722 2361,752q2385 659Q2384 712q2361 752);"/>
                        <Edge cubics="!2361 752(;2287,744 2274,746 2260,726q2361 752Q2295 745q2288 744Q2269 740q2260 726);"/>
                        <Edge cubics="!2260 726(;2206,649 2282,569 2385,659q2260 726Q2217 664q2264 630Q2312 595q2385 659);"/>
                        <Edge cubics="!1595 1625(;1622,1664 1607,1747 1604,1798q1595 1625Q1613 1650q1612 1707Q1606 1773q1604 1798);"/>
                        <Edge cubics="!1604 1798(;1530,1790 1520,1794 1504,1771q1604 1798Q1545 1792q1532 1790Q1515 1787q1504 1771);"/>
                        <Edge cubics="!1504 1771(;1476,1731 1478,1456 1595,1625q1504 1771Q1472 1725q1495 1619Q1518 1514q1595 1625);"/>
                        <Edge cubics="!1773 735(;1715,651 1799,506 1885,629q1773 735Q1726 667q1775 603Q1824 542q1885 629);"/>
                        <Edge cubics="!2561 1862(;2571,1876 2575,1854 2607,1900q2561 1862Q2563 1865q2576 1868Q2589 1873q2607 1900);"/>
                        <Edge cubics="!2607 1900(;2652,1965 2614,2081 2593,2155q2607 1900Q2636 1942q2625 2024Q2620 2062q2593 2155);"/>
                        <Edge cubics="!2111 2282(;2121,2296 2127,2275 2159,2321q2111 2282Q2113 2285q2128 2289Q2140 2294q2159 2321);"/>
                        <Edge cubics="!2159 2321(;2170,2338 2227,2442 2164,2486q2159 2321Q2179 2351q2189 2393Q2204 2459q2164 2486);"/>
                        <Edge cubics="!2014 2488(;2010,2442 2039,2340 2111,2282q2014 2488Q2011 2447q2033 2390Q2061 2321q2111 2282);"/>
                        <Edge cubics="!1606 187(;1600,218 1598,236 1601,239q1606 187Q1597 234q1601 239);"/>
                        <Edge cubics="!1608 177(;1607,179 1607,182 1606,187q1608 177Q1607 181q1606 187);"/>
                        <Edge cubics="!1655 199(;1647,187 1632,180 1608,177q1655 199Q1643 182q1608 177);"/>
                        <Edge cubics="!980 455(;960,453 942,451 926,448q980 455Q950 451q926 448);"/>
                        <Edge cubics="!932 483(;948,473 963,464 980,455q932 483Q956 468q980 455);"/>
                        <Edge cubics="!926 448(;927,461 929,472 932,483q926 448Q928 466q932 483);"/>
                        <Edge cubics="!1759 353(;1744,333 1730,312 1714,290q1759 353Q1737 323q1714 290);"/>
                        <Edge cubics="!1708 339(;1725,343 1742,348 1759,353q1708 339Q1734 346q1759 353);"/>
                        <Edge cubics="!1800 753(;1789,749 1779,744 1773,735q1800 753Q1782 748q1773 735);"/>
                        <Edge cubics="!1880 747(;1878,752 1875,757 1873,760q1880 747Q1877 754q1873 760);"/>
                        <Edge cubics="!1885 629(;1903,656 1902,695 1880,747q1885 629Q1912 669q1880 747);"/>
                        <Edge cubics="!1880 747(;1894,750 1906,755 1913,760q1880 747Q1903 752q1913 760);"/>
                        <Edge cubics="!1873 760(;1857,759 1845,758 1834,756q1873 760Q1850 758q1834 756);"/>
                        <Edge cubics="!1820 783(;1823,773 1827,764 1834,756q1820 783Q1823 768q1834 756);"/>
                        <Edge cubics="!1834 756(;1815,754 1803,752 1800,753q1834 756Q1805 753q1800 753);"/>
                        <Edge cubics="!1714 290(;1675,230 1655,200 1655,199q1714 290Q1656 200q1655 199);"/>
                        <Edge cubics="!1690 280(;1704,299 1710,320 1708,339q1690 280Q1711 310q1708 339);"/>
                        <Edge cubics="!715 558(;722,567 730,576 738,587q715 558Q727 570q738 587);"/>
                        <Edge cubics="!595 583(;629,516 669,508 715,558q595 583Q646 482q715 558);"/>
                        <Edge cubics="!715 558(;717,520 715,472 712,412q715 558Q717 501q712 412);"/>
                        <Edge cubics="!527 796(;557,808 582,805 604,790q527 796Q571 812q604 790);"/>
                        <Edge cubics="!604 790(;606,788 610,785 614,783q604 790Q608 787q614 783);"/>
                        <Edge cubics="!614 783(;596,778 581,767 571,751q614 783Q587 774q571 751);"/>
                        <Edge cubics="!435 756(;458,766 488,780 527,796q435 756Q470 770q527 796);"/>
                        <Edge cubics="!566 681(;570,644 580,611 595,583q566 681Q573 626q595 583);"/>
                        <Edge cubics="!571 751(;562,739 561,716 566,681q571 751Q558 734q566 681);"/>
                        <Edge cubics="!741 750(;692,784 650,795 614,783q741 750Q668 801q614 783);"/>
                        <Edge cubics="!314 915(;302,924 290,932 281,940q314 915Q295 928q281 940);"/>
                        <Edge cubics="!258 1133(;254,1133 250,1130 247,1128q258 1133Q252 1131q247 1128);"/>
                        <Edge cubics="!258 1137(;258,1135 258,1135 258,1133q258 1137Q258 1135q258 1133);"/>
                        <Edge cubics="!247 1128(;250,1131 254,1134 258,1137q247 1128Q252 1133q258 1137);"/>
                        <Edge cubics="!329 945(;355,949 384,954 413,959q329 945Q368 950q413 959);"/>
                        <Edge cubics="!413 959(;392,945 375,933 365,926q413 959Q381 936q365 926);"/>
                        <Edge cubics="!281 940(;296,940 312,942 329,945q281 940Q302 941q329 945);"/>
                        <Edge cubics="!157 798(;179,782 201,770 224,760q157 798Q190 775q224 760);"/>
                        <Edge cubics="!365 926(;342,911 326,907 314,915q365 926Q331 903q314 915);"/>
                        <Edge cubics="!979 1354(;985,1321 992,1287 1003,1252q979 1354Q987 1305q1003 1252);"/>
                        <Edge cubics="!1003 1252(;985,1281 971,1314 959,1353q1003 1252Q977 1295q959 1353);"/>
                        <Edge cubics="!959 1353(;966,1352 973,1353 979,1354q959 1353Q969 1352q979 1354);"/>
                        <Edge cubics="!224 760(;289,669 368,586 465,509q224 760Q321 624q465 509);"/>
                        <Edge cubics="!224 760(;296,728 367,726 435,756q224 760Q332 712q435 756);"/>
                        <Edge cubics="!1029 1660(;1027,1657 1024,1653 1023,1650q1029 1660Q1025 1655q1023 1650);"/>
                        <Edge cubics="!1068 1729(;1055,1706 1043,1683 1029,1660q1068 1729Q1049 1694q1029 1660);"/>
                        <Edge cubics="!981 1680(;1011,1698 1040,1714 1068,1729q981 1680Q1027 1706q1068 1729);"/>
                        <Edge cubics="!1023 1650(;997,1638 973,1626 949,1614q1023 1650Q984 1632q949 1614);"/>
                        <Edge cubics="!1814 2140(;1767,2072 1780,2037 1852,2037q1814 2140Q1744 2038q1852 2037);"/>
                        <Edge cubics="!1854 2187(;1825,2151 1811,2135 1814,2140q1854 2187Q1809 2132q1814 2140);"/>
                        <Edge cubics="!465 509(;554,430 643,360 733,299q465 509Q598 390q733 299);"/>
                        <Edge cubics="!712 412(;712,370 719,333 733,299q712 412Q713 349q733 299);"/>
                        <Edge cubics="!1852 2037(;1925,2037 1975,2056 2001,2094q1852 2037Q1962 2037q2001 2094);"/>
                        <Edge cubics="!226 1466(;226,1466 69,1205 69,1205q226 1466 69 1205);"/>
                        <Edge cubics="!24 1518(;16,1393 23,1277 47,1168q24 1518Q11 1332q47 1168);"/>
                        <Edge cubics="!130 1993(;70,1834 34,1675 24,1518q130 1993Q39 1753q24 1518);"/>
                        <Edge cubics="!275 1717(;251,1626 234,1541 226,1466q275 1717Q239 1579q226 1466);"/>
                        <Edge cubics="!304 1824(;293,1788 283,1752 275,1717q304 1824Q288 1770q275 1717);"/>
                        <Edge cubics="!47 1168(;16,1119 1,1076 0,1037q47 1168Q2 1095q0 1037);"/>
                        <Edge cubics="!69 1205(;61,1193 53,1181 47,1168q69 1205Q56 1186q47 1168);"/>
                        <Edge cubics="!594 2003(;590,2006 586,2009 582,2010q594 2003Q588 2008q582 2010);"/>
                        <Edge cubics="!509 2008(;513,2015 515,2033 515,2062q509 2008Q515 2017q515 2062);"/>
                        <Edge cubics="!408 2121(;388,2092 384,2063 395,2033q408 2121Q378 2077q395 2033);"/>
                        <Edge cubics="!534 2114(;527,2107 519,2100 513,2094q534 2114Q523 2103q513 2094);"/>
                        <Edge cubics="!513 2094(;511,2113 506,2131 500,2144q513 2094Q509 2123q500 2144);"/>
                        <Edge cubics="!395 2033(;402,2014 415,1999 433,1988q395 2033Q405 2004q433 1988);"/>
                        <Edge cubics="!433 1988(;403,1971 385,1957 376,1945q433 1988Q389 1963q376 1945);"/>
                        <Edge cubics="!635 2140(;612,2156 578,2148 534,2114q635 2140Q601 2163q534 2114);"/>
                        <Edge cubics="!582 2010(;614,2031 644,2057 673,2086q582 2010Q630 2042q673 2086);"/>
                        <Edge cubics="!433 1988(;443,1982 456,1977 471,1973q433 1988Q448 1978q471 1973);"/>
                        <Edge cubics="!515 2062(;514,2073 513,2084 513,2094q515 2062Q513 2078q513 2094);"/>
                        <Edge cubics="!413 2478(;376,2433 339,2386 305,2337q413 2478Q356 2411q305 2337);"/>
                        <Edge cubics="!413 2478(;413,2462 412,2446 413,2429q413 2478Q413 2455q413 2429);"/>
                        <Edge cubics="!678 2724(;551,2717 476,2698 454,2666q678 2724Q487 2713q454 2666);"/>
                        <Edge cubics="!692 2446(;673,2433 654,2420 637,2409q692 2446Q663 2426q637 2409);"/>
                        <Edge cubics="!609 2529(;682,2547 760,2550 844,2539q609 2529Q718 2555q844 2539);"/>
                        <Edge cubics="!844 2539(;847,2539 850,2539 854,2538q844 2539Q848 2539q854 2538);"/>
                        <Edge cubics="!854 2538(;800,2509 746,2478 692,2446q854 2538Q772 2494q692 2446);"/>
                        <Edge cubics="!637 2409(;636,2450 626,2489 609,2529q637 2409Q634 2470q609 2529);"/>
                        <Edge cubics="!413 2429(;414,2315 394,2229 353,2170q413 2429Q415 2258q353 2170);"/>
                        <Edge cubics="!454 2666(;429,2630 416,2567 413,2478q454 2666Q416 2611q413 2478);"/>
                        <Edge cubics="!756 2726(;727,2725 702,2725 678,2724q756 2726Q714 2725q678 2724);"/>
                        <Edge cubics="!305 2337(;237,2240 179,2125 130,1993q305 2337Q204 2192q130 1993);"/>
                        <Edge cubics="!353 2170(;274,2055 257,1939 304,1824q353 2170Q234 1998q304 1824);"/>
                        <Edge cubics="!1266 2971(;1242,2937 1230,2899 1232,2855q1266 2971Q1230 2920q1232 2855);"/>
                        <Edge cubics="!1286 2995(;1180,2975 1075,2942 973,2894q1286 2995Q1126 2965q973 2894);"/>
                        <Edge cubics="!1460 3062(;1380,3051 1321,3028 1286,2995q1460 3062Q1340 3047q1286 2995);"/>
                        <Edge cubics="!1286 2995(;1278,2987 1271,2980 1266,2971q1286 2995Q1274 2984q1266 2971);"/>
                        <Edge cubics="!1211 2765(;1195,2741 1194,2717 1207,2693q1211 2765Q1187 2729q1207 2693);"/>
                        <Edge cubics="!1232 2855(;1232,2831 1231,2808 1229,2787q1232 2855Q1231 2820q1229 2787);"/>
                        <Edge cubics="!1294 2821(;1269,2816 1247,2804 1229,2787q1294 2821Q1256 2813q1229 2787);"/>
                        <Edge cubics="!1229 2787(;1223,2780 1217,2773 1211,2765q1229 2787Q1220 2777q1211 2765);"/>
                        <Edge cubics="!2484 2019(;2488,1949 2514,1896 2561,1862q2484 2019Q2491 1914q2561 1862);"/>
                        <Edge cubics="!2483 2025(;2484,2023 2483,2021 2484,2019q2483 2025Q2483 2022q2484 2019);"/>
                        <Edge cubics="!2554 2152(;2538,2150 2525,2149 2520,2148q2554 2152Q2529 2150q2520 2148);"/>
                        <Edge cubics="!2593 2155(;2577,2154 2563,2153 2554,2152q2593 2155Q2569 2153q2554 2152);"/>
                        <Edge cubics="!2520 2148(;2510,2147 2503,2145 2501,2142q2520 2148Q2504 2146q2501 2142);"/>
                        <Edge cubics="!2675 2222(;2678,2260 2684,2287 2695,2303q2675 2222Q2679 2280q2695 2303);"/>
                        <Edge cubics="!2783 2235(;2782,2236 2782,2236 2781,2235q2783 2235Q2782 2236q2781 2235);"/>
                        <Edge cubics="!2746 2281(;2763,2270 2776,2255 2783,2235q2746 2281Q2771 2264q2783 2235);"/>
                        <Edge cubics="!2781 2235(;2742,2212 2712,2186 2691,2158q2781 2235Q2722 2201q2691 2158);"/>
                        <Edge cubics="!2684 2164(;2682,2170 2676,2177 2669,2184q2684 2164Q2680 2173q2669 2184);"/>
                        <Edge cubics="!2669 2184(;2671,2193 2673,2206 2675,2222q2669 2184Q2673 2198q2675 2222);"/>
                        <Edge cubics="!2687 2155(;2686,2157 2685,2160 2684,2164q2687 2155Q2686 2159q2684 2164);"/>
                        <Edge cubics="!2691 2158(;2689,2157 2688,2156 2687,2155q2691 2158Q2688 2156q2687 2155);"/>
                        <Edge cubics="!2501 2142(;2485,2119 2479,2080 2483,2025q2501 2142Q2477 2107q2483 2025);"/>
                        <Edge cubics="!2527 2378(;2454,2425 2392,2460 2340,2482q2527 2378Q2418 2449q2340 2482);"/>
                        <Edge cubics="!2416 2188(;2401,2166 2403,2133 2425,2092q2416 2188Q2393 2154q2425 2092);"/>
                        <Edge cubics="!2594 2497(;2578,2482 2563,2460 2549,2432q2594 2497Q2569 2475q2549 2432);"/>
                        <Edge cubics="!2671 2519(;2614,2572 2551,2622 2483,2669q2671 2519Q2586 2598q2483 2669);"/>
                        <Edge cubics="!2671 2519(;2641,2521 2616,2513 2594,2497q2671 2519Q2626 2521q2594 2497);"/>
                        <Edge cubics="!2857 2438(;2782,2490 2719,2517 2671,2519q2857 2438Q2744 2516q2671 2519);"/>
                        <Edge cubics="!2549 2432(;2539,2402 2532,2385 2527,2378q2549 2432Q2534 2388q2527 2378);"/>
                        <Edge cubics="!2425 2092(;2439,2064 2458,2042 2483,2025q2425 2092Q2446 2051q2483 2025);"/>
                        <Edge cubics="!2554 2152(;2540,2184 2529,2204 2522,2211q2554 2152Q2534 2200q2522 2211);"/>
                        <Edge cubics="!1920 2668(;1909,2653 1911,2628 1927,2597q1920 2668Q1903 2644q1927 2597);"/>
                        <Edge cubics="!2080 2506(;2061,2504 2045,2501 2032,2497q2080 2506Q2051 2504q2032 2497);"/>
                        <Edge cubics="!2225 2574(;2170,2612 2113,2644 2053,2670q2225 2574Q2143 2631q2053 2670);"/>
                        <Edge cubics="!2053 2670(;2052,2671 2052,2671 2052,2673q2053 2670Q2052 2671q2052 2673);"/>
                        <Edge cubics="!2032 2497(;2026,2495 2019,2490 2014,2488q2032 2497Q2022 2493q2014 2488);"/>
                        <Edge cubics="!2127 2503(;2128,2504 2128,2504 2129,2505q2127 2503Q2128 2504q2129 2505);"/>
                        <Edge cubics="!2164 2486(;2154,2493 2141,2499 2127,2503q2164 2486Q2148 2497q2127 2503);"/>
                        <Edge cubics="!2127 2503(;2112,2505 2097,2507 2080,2506q2127 2503Q2106 2507q2080 2506);"/>
                        <Edge cubics="!1927 2597(;1944,2560 1979,2528 2032,2497q1927 2597Q1952 2542q2032 2497);"/>
                        <Edge cubics="!1212 2683(;1225,2665 1243,2650 1269,2640q1212 2683Q1230 2656q1269 2640);"/>
                        <Edge cubics="!1269 2640(;1343,2608 1400,2621 1442,2681q1269 2640Q1380 2592q1442 2681);"/>
                        <Edge cubics="!1918 2924(;1891,2943 1863,2961 1835,2976q1918 2924Q1877 2953q1835 2976);"/>
                        <Edge cubics="!2052 2673(;2027,2797 1982,2880 1918,2924q2052 2673Q2014 2858q1918 2924);"/>
                        <Edge cubics="!2340 2482(;2305,2515 2267,2545 2225,2574q2340 2482Q2287 2531q2225 2574);"/>
                        <Edge cubics="!2483 2669(;2263,2821 2047,2924 1835,2976q2483 2669Q2153 2898q1835 2976);"/>
                        <Edge cubics="!973 2894(;866,2846 768,2790 678,2724q973 2894Q813 2823q678 2724);"/>
                        <Edge cubics="!0 1037(;-2,952 50,872 157,798q0 1037Q-3 909q157 798);"/>
                        <Edge cubics="!1204 2681(;1073,2713 923,2727 756,2726q1204 2681Q1007 2728q756 2726);"/>
                        <Edge cubics="!1835 2976(;1704,3051 1578,3080 1460,3062q1835 2976Q1638 3088q1460 3062);"/>
                        <Edge cubics="!1977 2198(;1937,2225 1896,2221 1854,2187q1977 2198Q1917 2239q1854 2187);"/>
                        <Edge cubics="!1212 2683(;1209,2683 1207,2682 1204,2681q1212 2683Q1207 2682q1204 2681);"/>
                        <Edge cubics="!1207 2693(;1209,2690 1210,2686 1212,2683q1207 2693Q1210 2689q1212 2683);"/>
                        <Edge cubics="!1437 2784(;1385,2820 1338,2832 1294,2821q1437 2784Q1359 2838q1294 2821);"/>
                        <Edge cubics="!1715 17(;1735,27 1753,43 1770,68q1715 17Q1744 31q1770 68);"/>
                        <Edge cubics="!1770 68(;1778,80 1786,92 1794,108q1770 68Q1782 86q1794 108);"/>
                        <Edge cubics="!2016 137(;2081,163 2147,192 2210,226q2016 137Q2115 175q2210 226);"/>
                        <Edge cubics="!2130 261(;2155,243 2181,231 2210,226q2130 261Q2167 235q2210 226);"/>
                        <Edge cubics="!1770 68(;1851,82 1934,106 2016,137q1770 68Q1893 91q2016 137);"/>
                        <Edge cubics="!1794 108(;1831,185 1860,237 1878,264q1794 108Q1850 223q1878 264);"/>
                        <Edge cubics="!2592 393(;2699,488 2793,594 2874,712q2592 393Q2752 536q2874 712);"/>
                        <Edge cubics="!2225 615(;2221,616 2220,618 2217,618q2225 615Q2221 617q2217 618);"/>
                        <Edge cubics="!2227 618(;2226,617 2225,616 2225,615q2227 618Q2225 616q2225 615);"/>
                        <Edge cubics="!2217 618(;2226,625 2234,633 2241,639q2217 618Q2229 628q2241 639);"/>
                        <Edge cubics="!2241 639(;2236,632 2231,624 2227,618q2241 639Q2234 628q2227 618);"/>
                        <Edge cubics="!2816 1251(;2828,1253 2839,1254 2852,1258q2816 1251Q2832 1253q2852 1258);"/>
                        <Edge cubics="!2865 1417(;2864,1419 2866,1421 2867,1423q2865 1417Q2865 1420q2867 1423);"/>
                        <Edge cubics="!2914 1432(;2896,1429 2880,1424 2865,1417q2914 1432Q2888 1428q2865 1417);"/>
                        <Edge cubics="!2865 1417(;2853,1413 2843,1407 2831,1402q2865 1417Q2847 1410q2831 1402);"/>
                        <Edge cubics="!2905 1276(;2935,1291 2952,1299 2954,1301q2905 1276Q2951 1297q2954 1301);"/>
                        <Edge cubics="!2852 1258(;2867,1263 2885,1269 2905,1276q2852 1258Q2876 1265q2905 1276);"/>
                        <Edge cubics="!2804 1381(;2736,1283 2740,1240 2816,1251q2804 1381Q2702 1234q2816 1251);"/>
                        <Edge cubics="!2831 1402(;2831,1402 2804,1381 2804,1381q2831 1402 2804 1381);"/>
                        <Edge cubics="!2904 915(;2917,945 2931,978 2945,1014q2904 915Q2924 961q2945 1014);"/>
                        <Edge cubics="!2904 915(;2900,962 2892,1014 2880,1073q2904 915Q2898 984q2880 1073);"/>
                        <Edge cubics="!2874 712(;2901,751 2911,818 2904,915q2874 712Q2915 770q2904 915);"/>
                        <Edge cubics="!2880 1073(;2866,1146 2855,1207 2852,1258q2880 1073Q2858 1181q2852 1258);"/>
                        <Edge cubics="!2210 226(;2314,204 2440,260 2592,393q2210 226Q2366 194q2592 393);"/>
                        <Edge cubics="!2843 1688(;2848,1726 2852,1747 2853,1748q2843 1688Q2851 1746q2853 1748);"/>
                        <Edge cubics="!2871 1768(;2867,1743 2857,1716 2843,1688q2871 1768Q2864 1731q2843 1688);"/>
                        <Edge cubics="!2814 1765(;2814,1769 2815,1775 2814,1781q2814 1765Q2814 1772q2814 1781);"/>
                        <Edge cubics="!2814 1781(;2816,1781 2819,1782 2821,1782q2814 1781Q2818 1781q2821 1782);"/>
                        <Edge cubics="!2821 1782(;2819,1776 2816,1770 2814,1765q2821 1782Q2817 1773q2814 1765);"/>
                        <Edge cubics="!2853 1748(;2857,1755 2863,1762 2871,1768q2853 1748Q2860 1758q2871 1768);"/>
                        <Edge cubics="!3033 1896(;3048,1941 3062,1971 3074,1989q3033 1896Q3056 1963q3074 1989);"/>
                        <Edge cubics="!3057 1517(;3066,1651 3058,1778 3033,1896q3057 1517Q3070 1719q3033 1896);"/>
                        <Edge cubics="!2978 1719(;2998,1791 3017,1851 3033,1896q2978 1719Q3008 1828q3033 1896);"/>
                        <Edge cubics="!2945 1014(;3008,1184 3045,1351 3057,1517q2945 1014Q3040 1269q3057 1517);"/>
                        <Edge cubics="!2867 1423(;2898,1472 2936,1571 2978,1719q2867 1423Q2914 1497q2978 1719);"/>
                        <Edge cubics="!1112 68(;1447,0 1648,-18 1715,17q1112 68Q1615 -33q1715 17);"/>
                        <Edge cubics="!785 219(;845,155 954,104 1112,68q785 219Q876 123q1112 68);"/>
                        <Edge cubics="!733 299(;746,270 763,242 785,219q733 299Q752 254q785 219);"/>
                      </edges>
                    </DOMShape>
                  </members>
                </DOMGroup>
              </elements>
            </DOMFrame>
          </frames>
        </DOMLayer>
      </layers>
    </DOMTimeline>
  </timeline>
</DOMSymbolItem>