<DOMSymbolItem xmlns:xsi="http://www.w3.org/2001/XMLSchema-instance" xmlns="http://ns.adobe.com/xfl/2008/" name="Symbol 7" itemID="54845979-000007c0" lastModified="1417987809">
  <timeline>
    <DOMTimeline name="Symbol 7">
      <layers>
        <DOMLayer name="Layer 3" color="#FF800A">
          <frames>
            <DOMFrame index="0" keyMode="9728">
              <elements>
                <DOMShape>
                  <fills>
                    <FillStyle index="1">
                      <SolidColor color="#754C1D" alpha="0.976470588235294"/>
                    </FillStyle>
                    <FillStyle index="2">
                      <SolidColor color="#BD9C77" alpha="0.976470588235294"/>
                    </FillStyle>
                    <FillStyle index="3">
                      <SolidColor color="#633F17" alpha="0.976470588235294"/>
                    </FillStyle>
                  </fills>
                  <edges>
                    <Edge fillStyle0="1" fillStyle1="2" edges="!704 1152[697 1170 689 1178!689 1178[676 1192 644 1192!644 1192[607 1192 500 1150!500 1150[395 1109 359 1082!359 1082[354 1067 354 1037!354 1037[425 1037 527 1057!527 1057[691 1089 704 1152"/>
                    <Edge fillStyle0="1" edges="!695 1724[865 1683 950 1572!950 1572[#400.06 #5C2.FA 1025 1391!1025 1391[#401.EC #51B.11 1004.5 1125.5!1004.5 1125.5[#3D7.13 #3AF.EE 591.5 945!591.5 945[#C7.F9 #3B2.05 -39 1008!-39 1008[-236 1065 -236 1062!-236 1062[-236 1086 -161 1194
!-161 1194[-80 1310 23 1426!23 1426|24 1427!24 1427[309 1747 474 1747!474 1747[534 1747 588 1742"/>
                    <Edge fillStyle0="1" fillStyle1="3" edges="
!588 1742[381 1731 94 1447!94 1447[-7 1346 -93 1237!-93 1237[-166 1142 -166 1127!-166 1127[-166 1090 -61 1121!-61 1121[-16 1134 204 1217!204 1217[666 1392 904 1392!904 1392[956 1392 980 1439!980 1439[994 1467 994 1492!994 1492[994 1524
 860 1627!860 1627[769 1696 695 1724"/>
                    <Edge fillStyle1="3" edges="
!695 1724[646 1742 604 1742!604 1742[596 1742 588 1742"/>
                    <Edge cubics="!904 1392(;986,1392 994,1484 994,1492q904 1392Q956 1392q980 1439Q994 1467q994 1492);"/>
                    <Edge cubics="!-166 1127(;-166,1014 464,1392 904,1392q-166 1127Q-166 1090q-61 1121Q-16 1134q204 1217Q666 1392q904 1392);"/>
                    <Edge cubics="!704 1152(;694,1167 694,1192 644,1192q704 1152Q697 1170q689 1178Q676 1192q644 1192);"/>
                    <Edge cubics="!644 1192(;594,1192 406,1117 359,1082q644 1192Q607 1192q500 1150Q395 1109q359 1082);"/>
                    <Edge cubics="!359 1082(;354,1067 354,1042 354,1037q359 1082Q354 1067q354 1037);"/>
                    <Edge cubics="!354 1037(;369,1037 684,1052 704,1152q354 1037Q425 1037q527 1057Q691 1089q704 1152);"/>
                    <Edge cubics="!-39 1008(;120,967 265,941 394,932q-39 1008Q200 946q394 932);"/>
                    <Edge cubics="!-93 1237(;-142,1174 -166,1137 -166,1127q-93 1237Q-166 1142q-166 1127);"/>
                    <Edge cubics="!23 1426(;-46,1349 -107,1271 -161,1194q23 1426Q-80 1310q-161 1194);"/>
                    <Edge cubics="!24 1427(;23,1426 23,1426 23,1426q24 1427Q23 1426q23 1426);"/>
                    <Edge cubics="!-161 1194(;-211,1122 -236,1078 -236,1062q-161 1194Q-236 1086q-236 1062);"/>
                    <Edge cubics="!94 1447(;27,1380 -36,1310 -93,1237q94 1447Q-7 1346q-93 1237);"/>
                    <Edge cubics="!-236 1062(;-236,1064 -170,1046 -39,1008q-236 1062Q-236 1065q-39 1008);"/>
                    <Edge cubics="!1019 1264(;1022,1288 1024,1313 1024,1339q1019 1264Q1024 1300q1024 1339);"/>
                    <Edge cubics="!588 1742(;552,1745 514,1747 474,1747q588 1742Q534 1747q474 1747);"/>
                    <Edge cubics="!1024 1339(;1024,1430 999,1507 950,1572q1024 1339Q1024 1475q950 1572);"/>
                    <Edge cubics="!950 1572(;893,1646 808,1697 695,1724q950 1572Q865 1683q695 1724);"/>
                    <Edge cubics="!860 1627(;799,1673 744,1705 695,1724q860 1627Q769 1696q695 1724);"/>
                    <Edge cubics="!994 1492(;994,1513 949,1558 860,1627q994 1492Q994 1524q860 1627);"/>
                    <Edge cubics="!394 932(;777,905 986,1015 1019,1264q394 932Q969 891q1019 1264);"/>
                    <Edge cubics="!474 1747(;364,1747 214,1640 24,1427q474 1747Q309 1747q24 1427);"/>
                    <Edge cubics="!588 1742(;450,1735 285,1636 94,1447q588 1742Q381 1731q94 1447);"/>
                    <Edge cubics="!695 1724(;662,1736 632,1742 604,1742q695 1724Q646 1742q604 1742);"/>
                    <Edge cubics="!604 1742(;599,1742 593,1742 588,1742q604 1742Q596 1742q588 1742);"/>
                  </edges>
                </DOMShape>
              </elements>
            </DOMFrame>
          </frames>
        </DOMLayer>
        <DOMLayer name="Layer 1" color="#4FFF4F" current="true" isSelected="true">
          <frames>
            <DOMFrame index="0" keyMode="9728">
              <elements>
                <DOMShape>
                  <fills>
                    <FillStyle index="1">
                      <SolidColor alpha="0.976470588235294"/>
                    </FillStyle>
                  </fills>
                  <edges>
                    <Edge fillStyle1="1" edges="
!1628 443[1631 441 1636 426!1636 426[1640 410 1661 390!1661 390[1684 369 1930 510!1930 510[2167 646 2193 679!2193 679[2191 681 2190 694!2190 694[2188 706 2167 726!2167 726[2143 748 1947 665!1947 665[1743 579 1675 508!1675 508[1654 485
 1639 462!1639 462|1628 443!1882 966[1895 985 1895 1003!1895 1003[#766.E3 #41B.F3 1894 1054.5!1894 1054.5[#765.5 #421.0A 1738.5 1024!1738.5 1024[#62F.AF #3DE.F4 1524.5 1014.5!1524.5 1014.5[#5B9.1C #40E.0B 1465 1006!1465 1006[1465 958
 1504 942!1504 942[1579 910 1820 926!1820 926[1862 939 1882 966!860 437[716 477 686 448!686 448[600 361 842 259!842 259[930 221 1019 201!1019 201[1107 183 1119 195!1119 195[1137 213 1137 241!1137 241[1136 276 1104 308!1104 308[1017 394
 860 437!974 956|780 1016!780 1016[722 979 718 976!718 976[696 961 694 946!694 946[685 896 748 869!748 869[#323.F1 #34E.18 889.5 841!889.5 841[#3CF.2B #343.B5 1042.5 857!1042.5 857[#455.D4 #36E.4A 1123 949.5!1123 949.5[#470.0E #3FC.E7
 974 956!1500 2039[1595 1906 1705 1939!1705 1939[1803 1967 1803 2042!1803 2042[1803 2084 1767 2122!1767 2122[1722 2167 1652 2167!1652 2167[1593 2167 1572 2157!1572 2157[1548 2141 1519 2129!1519 2129|1500 2039"/>
                    <Edge cubics="!1820 926(;1885,946 1895,988 1895,1003q1820 926Q1862 939q1882 966Q1895 985q1895 1003);"/>
                    <Edge cubics="!1465 1006(;1465,966 1450,901 1820,926q1465 1006Q1465 958q1504 942Q1579 910q1820 926);"/>
                    <Edge cubics="!1119 195(;1138,214 1151,261 1104,308q1119 195Q1137 213q1137 241Q1136 276q1104 308);"/>
                    <Edge cubics="!1104 308(;977,433 719,481 686,448q1104 308Q1017 394q860 437Q716 477q686 448);"/>
                    <Edge cubics="!686 448(;556,316 1085,161 1119,195q686 448Q600 361q842 259Q930 221q1019 201Q1107 183q1119 195);"/>
                    <Edge cubics="!2193 679(;2183,690 2203,692 2167,726q2193 679Q2191 681q2190 694Q2188 706q2167 726);"/>
                    <Edge cubics="!2167 726(;2139,752 1771,610 1675,508q2167 726Q2143 748q1947 665Q1743 579q1675 508);"/>
                    <Edge cubics="!1675 508(;1641,471 1628,443 1628,443q1675 508Q1654 485q1639 462Q1628 443q1628 443);"/>
                    <Edge cubics="!1628 443(;1639,432 1625,425 1661,390q1628 443Q1631 441q1636 426Q1640 410q1661 390);"/>
                    <Edge cubics="!1661 390(;1696,358 2167,646 2193,679q1661 390Q1684 369q1930 510Q2167 646q2193 679);"/>
                    <Edge cubics="!1803 2042(;1803,2087 1756,2167 1652,2167q1803 2042Q1803 2084q1767 2122Q1722 2167q1652 2167);"/>
                    <Edge cubics="!1652 2167(;1557,2167 1576,2152 1519,2129q1652 2167Q1593 2167q1572 2157Q1548 2141q1519 2129);"/>
                    <Edge cubics="!1519 2129(;1519,2129 1500,2039 1500,2039q1519 2129 1500 2039);"/>
                    <Edge cubics="!1500 2039(;1642,1836 1803,1972 1803,2042q1500 2039Q1595 1906q1705 1939Q1803 1967q1803 2042);"/>
                    <Edge cubics="!780 1016(;725,981 697,968 694,946q780 1016Q722 979q718 976Q696 961q694 946);"/>
                    <Edge cubics="!694 946(;670,803 1104,828 1123,943q694 946Q685 896q748 869Q804 846q892 848Q979 850q1045 875Q1116 902q1123 943);"/>
                    <Edge cubics="!1123 943(;1132,995 1083,999 974,956q1123 943Q1136 1021q974 956);"/>
                    <Edge cubics="!974 956(;974,956 780,1016 780,1016q974 956 780 1016);"/>
                    <Edge cubics="!1894 1055(;1893,1056 1842,1046 1739,1024q1894 1055Q1893 1057q1739 1024);"/>
                    <Edge cubics="!1895 1003(;1895,1036 1895,1053 1894,1055q1895 1003Q1895 1052q1894 1055);"/>
                    <Edge cubics="!1525 1015(;1485,1030 1465,1027 1465,1006q1525 1015Q1465 1038q1465 1006);"/>
                    <Edge cubics="!1739 1024(;1636,1002 1564,999 1525,1015q1739 1024Q1584 991q1525 1015);"/>
                  </edges>
                </DOMShape>
              </elements>
            </DOMFrame>
          </frames>
        </DOMLayer>
        <DOMLayer name="Layer 2" color="#9933CC">
          <frames>
            <DOMFrame index="0" keyMode="9728">
              <elements>
                <DOMGroup>
                  <members>
                    <DOMShape>
                      <fills>
                        <FillStyle index="1">
                          <SolidColor color="#D0AD42" alpha="0.976470588235294"/>
                        </FillStyle>
                        <FillStyle index="2">
                          <SolidColor color="#E3BF52" alpha="0.976470588235294"/>
                        </FillStyle>
                        <FillStyle index="3">
                          <SolidColor color="#B59635" alpha="0.976470588235294"/>
                        </FillStyle>
                      </fills>
                      <edges>
                        <Edge fillStyle1="1" edges="
!2343 331[2401 326 2502 396!2502 396[2706 537 2877 794!2877 794[2959 884 3022 1326!3022 1326[3022 1569 2977 1714!2977 1714[2975 1722 2797 2174!2797 2174[2690 2448 2537 2594!2537 2594[2445 2682 2077 2772!2077 2772[1526 2906 1502 2914!1502
 2914|902 2914!902 2914[562 2879 320 2269!320 2269[267 2137 226 1995"/>
                        <Edge fillStyle1="2" edges="
!226 1995[176 1877 143 1746!143 1746[102 1584 102 1496!102 1496[102 1184 206 891!206 891[307 606 486 392!486 392[669 174 897 72!897 72[1139 -36 1392 4!1392 4[1664 87 1897 218!1897 218[1976 213 2061 221!2061 221[2159 229 2197 244!2197
 244[2272 283 2343 331"/>
                        <Edge fillStyle0="2" fillStyle1="1" edges="
!226 1995[198 1896 175 1792!175 1792[127 1572 127 1449!127 1449[127 1262 201 1092!201 1092[322 816 362 674!362 674[401 702 415 742!415 742[429 735 442 734!442 734[455 739 476 739!476 739[492 743 492 774!492 774[492 798 418 941!418 941
[395 985 379 1020!379 1020[362 1074 337 1156!337 1156[335 1162 334 1167!334 1167[328 1227 320 1319!320 1319[308 1418 272 1489!272 1489|268 1491!268 1491[280 1580 312 1703!312 1703[373 1932 472 2127!472 2127[749 2669 1177 2664!1177 2664
|1682 2664!1682 2664[2238 2607 2533 2062!2533 2062[2640 1865 2697 1629!2697 1629[2742 1442 2742 1304!2742 1304[2742 1137 2502 833!2502 833[2382 686 2337 627!2337 627[2262 527 2262 486!2262 486[2262 338 2343 331"/>
                        <Edge fillStyle0="1" fillStyle1="3" edges="
!1665 1760[1552 1931 1286 1931!1286 1931[1051 1931 971 1753!971 1753[932 1667 932 1511!932 1511[938 1419 980 1329!980 1329[1063 1150 1243 1150!1243 1150[1731 1150 1731 1538!1731 1538[1731 1659 1665 1760"/>
                        <Edge fillStyle0="2" fillStyle1="1" edges="
!1913 1520[1938 1585 1952 1654!1952 1654[1952 1804 1823 1895!1823 1895[1644 2019 1232 2019!1232 2019[929 2019 843 1829!843 1829[816 1769 814 1697!814 1697[817 1636 817 1634!817 1634[817 1593 821 1553!821 1553[718 1437 637 1321!637 1321
[562 1213 562 1189!562 1189[562 1192 759 1135!759 1135[998 1073 1192 1059!1192 1059[1767 1018 1817 1391!1817 1391[1869 1406 1913 1520"/>
                        <Edge cubics="!102 1496(;102,651 697,-106 1392,4q102 1496Q102 1184q206 891Q307 606q486 392Q669 174q897 72Q1139 -36q1392 4);"/>
                        <Edge cubics="!442 734(;467,744 492,724 492,774q442 734Q455 739q476 739Q492 743q492 774);"/>
                        <Edge cubics="!3022 1326(;3022,1689 2977,1716 2797,2174q3022 1326Q3022 1569q2977 1714Q2975 1722q2797 2174);"/>
                        <Edge cubics="!2797 2174(;2742,2314 2662,2474 2537,2594q2797 2174Q2690 2448q2537 2594);"/>
                        <Edge cubics="!2537 2594(;2382,2741 1809,2814 1502,2914q2537 2594Q2445 2682q2077 2772Q1526 2906q1502 2914);"/>
                        <Edge cubics="!1502 2914(;1502,2914 902,2914 902,2914q1502 2914 902 2914);"/>
                        <Edge cubics="!127 1449(;127,1121 247,1084 362,674q127 1449Q127 1262q201 1092Q322 816q362 674);"/>
                        <Edge cubics="!1177 2664(;1177,2664 1682,2664 1682,2664q1177 2664 1682 2664);"/>
                        <Edge cubics="!1682 2664(;2537,2576 2742,1601 2742,1304q1682 2664Q2238 2607q2533 2062Q2640 1865q2697 1629Q2742 1442q2742 1304);"/>
                        <Edge cubics="!2742 1304(;2742,1011 2262,614 2262,486q2742 1304Q2742 1137q2502 833Q2382 686q2337 627Q2262 527q2262 486);"/>
                        <Edge cubics="!2877 794(;2959,884 3022,1296 3022,1326q2877 794Q2959 884q3022 1326);"/>
                        <Edge cubics="!1952 1654(;1952,1809 1847,2019 1232,2019q1952 1654Q1952 1804q1823 1895Q1644 2019q1232 2019);"/>
                        <Edge cubics="!1232 2019(;747,2019 817,1641 817,1634q1232 2019Q929 2019q843 1829Q816 1769q814 1697Q817 1636q817 1634);"/>
                        <Edge cubics="!1702 1519(;1784,1519 1792,1611 1792,1619q1702 1519Q1754 1519q1778 1566Q1792 1594q1792 1619);"/>
                        <Edge cubics="!632 1254(;632,1141 1262,1519 1702,1519q632 1254Q632 1217q737 1248Q782 1261q1002 1344Q1464 1519q1702 1519);"/>
                        <Edge cubics="!1502 1279(;1492,1294 1492,1319 1442,1319q1502 1279Q1495 1297q1487 1305Q1474 1319q1442 1319);"/>
                        <Edge cubics="!1442 1319(;1392,1319 1204,1244 1157,1209q1442 1319Q1405 1319q1298 1277Q1193 1236q1157 1209);"/>
                        <Edge cubics="!1157 1209(;1152,1194 1152,1169 1152,1164q1157 1209Q1152 1194q1152 1164);"/>
                        <Edge cubics="!1152 1164(;1167,1164 1482,1179 1502,1279q1152 1164Q1223 1164q1325 1184Q1489 1216q1502 1279);"/>
                        <Edge cubics="!759 1135(;918,1094 1063,1068 1192,1059q759 1135Q998 1073q1192 1059);"/>
                        <Edge cubics="!418 941(;403,970 390,997 379,1020q418 941Q395 985q379 1020);"/>
                        <Edge cubics="!379 1020(;368,1056 354,1101 337,1156q379 1020Q362 1074q337 1156);"/>
                        <Edge cubics="!362 674(;388,693 406,715 415,742q362 674Q401 702q415 742);"/>
                        <Edge cubics="!143 1746(;116,1638 102,1555 102,1496q143 1746Q102 1584q102 1496);"/>
                        <Edge cubics="!268 1491(;276,1550 291,1621 312,1703q268 1491Q280 1580q312 1703);"/>
                        <Edge cubics="!175 1792(;143,1645 127,1531 127,1449q175 1792Q127 1572q127 1449);"/>
                        <Edge cubics="!226 1995(;193,1916 165,1833 143,1746q226 1995Q176 1877q143 1746);"/>
                        <Edge cubics="!226 1995(;207,1929 190,1861 175,1792q226 1995Q198 1896q175 1792);"/>
                        <Edge cubics="!320 1319(;312,1385 296,1442 272,1489q320 1319Q308 1418q272 1489);"/>
                        <Edge cubics="!272 1489(;272,1489 268,1491 268,1491q272 1489 268 1491);"/>
                        <Edge cubics="!334 1167(;330,1207 325,1258 320,1319q334 1167Q328 1227q320 1319);"/>
                        <Edge cubics="!705 1364(;656,1301 632,1264 632,1254q705 1364Q632 1269q632 1254);"/>
                        <Edge cubics="!821 1553(;752,1476 691,1398 637,1321q821 1553Q718 1437q637 1321);"/>
                        <Edge cubics="!822 1554(;821,1553 821,1553 821,1553q822 1554Q821 1553q821 1553);"/>
                        <Edge cubics="!817 1634(;817,1607 818,1580 821,1553q817 1634Q817 1593q821 1553);"/>
                        <Edge cubics="!637 1321(;587,1249 562,1205 562,1189q637 1321Q562 1213q562 1189);"/>
                        <Edge cubics="!892 1574(;825,1507 762,1437 705,1364q892 1574Q791 1473q705 1364);"/>
                        <Edge cubics="!492 774(;492,790 467,846 418,941q492 774Q492 798q418 941);"/>
                        <Edge cubics="!415 742(;424,737 433,735 442,734q415 742Q429 735q442 734);"/>
                        <Edge cubics="!312 1703(;353,1856 406,1997 472,2127q312 1703Q373 1932q472 2127);"/>
                        <Edge cubics="!337 1156(;336,1160 335,1164 334,1167q337 1156Q335 1162q334 1167);"/>
                        <Edge cubics="!562 1189(;562,1191 628,1173 759,1135q562 1189Q562 1192q759 1135);"/>
                        <Edge cubics="!2343 331(;2382,328 2435,349 2502,396q2343 331Q2401 326q2502 396);"/>
                        <Edge cubics="!2061 221(;2126,226 2172,234 2197,244q2061 221Q2159 229q2197 244);"/>
                        <Edge cubics="!2197 244(;2247,270 2296,299 2343,331q2197 244Q2272 283q2343 331);"/>
                        <Edge cubics="!2262 486(;2262,387 2289,336 2343,331q2262 486Q2262 338q2343 331);"/>
                        <Edge cubics="!1817 1391(;1820,1415 1822,1440 1822,1466q1817 1391Q1822 1427q1822 1466);"/>
                        <Edge cubics="!1817 1391(;1852,1401 1884,1444 1913,1520q1817 1391Q1869 1406q1913 1520);"/>
                        <Edge cubics="!1913 1520(;1930,1563 1943,1608 1952,1654q1913 1520Q1938 1585q1952 1654);"/>
                        <Edge cubics="!1493 1851(;1460,1863 1430,1869 1402,1869q1493 1851Q1444 1869q1402 1869);"/>
                        <Edge cubics="!1386 1869(;1350,1872 1312,1874 1272,1874q1386 1869Q1332 1874q1272 1874);"/>
                        <Edge cubics="!1402 1869(;1397,1869 1391,1869 1386,1869q1402 1869Q1394 1869q1386 1869);"/>
                        <Edge cubics="!1822 1466(;1822,1557 1797,1634 1748,1699q1822 1466Q1822 1602q1748 1699);"/>
                        <Edge cubics="!1748 1699(;1691,1773 1606,1824 1493,1851q1748 1699Q1663 1810q1493 1851);"/>
                        <Edge cubics="!1658 1754(;1597,1800 1542,1832 1493,1851q1658 1754Q1567 1823q1493 1851);"/>
                        <Edge cubics="!1792 1619(;1792,1640 1747,1685 1658,1754q1792 1619Q1792 1651q1658 1754);"/>
                        <Edge cubics="!1897 218(;1950,215 2004,216 2061,221q1897 218Q1976 213q2061 221);"/>
                        <Edge cubics="!1392 4(;1573,59 1742,131 1897,218q1392 4Q1664 87q1897 218);"/>
                        <Edge cubics="!1192 1059(;1575,1032 1784,1142 1817,1391q1192 1059Q1767 1018q1817 1391);"/>
                        <Edge cubics="!1272 1874(;1162,1874 1012,1767 822,1554q1272 1874Q1107 1874q822 1554);"/>
                        <Edge cubics="!1386 1869(;1248,1862 1083,1763 892,1574q1386 1869Q1179 1858q892 1574);"/>
                        <Edge cubics="!2502 396(;2638,490 2763,623 2877,794q2502 396Q2706 537q2877 794);"/>
                        <Edge cubics="!902 2914(;675,2891 481,2676 320,2269q902 2914Q562 2879q320 2269);"/>
                        <Edge cubics="!472 2127(;657,2488 892,2667 1177,2664q472 2127Q749 2669q1177 2664);"/>
                        <Edge cubics="!320 2269(;285,2181 253,2090 226,1995q320 2269Q267 2137q226 1995);"/>
                        <Edge cubics="!1243 1150(;1703,1150 1731,1413 1731,1538q1243 1150Q1731 1150q1731 1538);"/>
                        <Edge cubics="!1731 1538(;1731,1606 1702,1931 1286,1931q1731 1538Q1731 1659q1665 1760Q1552 1931q1286 1931);"/>
                        <Edge cubics="!1286 1931(;917,1931 932,1597 932,1511q1286 1931Q1051 1931q971 1753Q932 1667q932 1511);"/>
                        <Edge cubics="!932 1511(;932,1507 956,1150 1243,1150q932 1511Q938 1419q980 1329Q1063 1150q1243 1150);"/>
                      </edges>
                    </DOMShape>
                  </members>
                </DOMGroup>
              </elements>
            </DOMFrame>
          </frames>
        </DOMLayer>
      </layers>
    </DOMTimeline>
  </timeline>
</DOMSymbolItem>