<DOMSymbolItem xmlns:xsi="http://www.w3.org/2001/XMLSchema-instance" xmlns="http://ns.adobe.com/xfl/2008/" name="Symbol 10" itemID="5484628e-00000261" lastModified="1417986598">
  <timeline>
    <DOMTimeline name="Symbol 10">
      <layers>
        <DOMLayer name="Layer 1" color="#4FFF4F" current="true" isSelected="true">
          <frames>
            <DOMFrame index="0" keyMode="9728">
              <elements>
                <DOMShape>
                  <fills>
                    <FillStyle index="1">
                      <SolidColor alpha="0.976470588235294"/>
                    </FillStyle>
                    <FillStyle index="2">
                      <SolidColor color="#FFFFFF" alpha="0.976470588235294"/>
                    </FillStyle>
                    <FillStyle index="3">
                      <SolidColor color="#1A1717" alpha="0.976470588235294"/>
                    </FillStyle>
                    <FillStyle index="4">
                      <SolidColor color="#060502" alpha="0.976470588235294"/>
                    </FillStyle>
                    <FillStyle index="5">
                      <SolidColor color="#F27777" alpha="0.976470588235294"/>
                    </FillStyle>
                    <FillStyle index="6">
                      <SolidColor color="#DB6565" alpha="0.976470588235294"/>
                    </FillStyle>
                    <FillStyle index="7">
                      <SolidColor color="#ECEAE5" alpha="0.976470588235294"/>
                    </FillStyle>
                  </fills>
                  <edges>
                    <Edge fillStyle1="1" edges="!1932 668[1964 652 2001 637!2001 637[2050 616 2097 599!2097 599[2181 568 2259 551!2259 551[2385 523 2408 549!2408 549[2442 586 2428 622!2428 622[2422 646 2393 675!2393 675[2387 680 2382 685!2382 685[2370 696 2347 708!2347 708[2290 739
 2167 777!2167 777[2120 791 2064 807!2064 807[2046 811 2029 816!2029 816[1903 850 1832 867!1832 867[1743 887 1737 881!1737 881[1693 833 1779 760!1779 760[1824 722 1895 686!1895 686[1913 677 1932 668"/>
                    <Edge fillStyle0="2" fillStyle1="7" edges="
!1666.5 1671[#680.4A #684.AF 1662 1666!1662 1666[1630 1628 1630 1623!1630 1623[1630 1611 1641 1606!1641 1606[1649 1602 1656 1602!1656 1602[1673 1602 1738 1629!1738 1629[1803 1656 1834 1656!1834 1656[1881 1656 2015 1647!2015 1647[2148
 1638 2154 1638!2154 1638[2258 1638 2325 1516!2325 1516[2373 1430 2373 1386!2373 1386[2373 1362 2363 1335!2363 1335[2354 1310 2356 1273!2356 1273[2339 1236 2299 1208!2299 1208|2262 1182!2262 1182[2262 #489.7B 2284.5 1153.5"/>
                    <Edge fillStyle0="2" edges="
!2284.5 1153.5[#8EB.B7 #481.5C 2283 1153!2283 1153[2016 1017 1815 1017!1815 1017[1759 1017 1722 1026!1722 1026[#693.4E #40B.9F 1653 1043!1653 1043[#63F.06 #446.29 1566 1174!1566 1174[1521 1286 1524 1406!1524 1406[1524 1493 1582 1584!1582
 1584[#651.C #667.9 1666.5 1671"/>
                    <Edge fillStyle1="7" edges="
!2284.5 1153.5[#8FA.1 1149 2320 1149!2320 1149[2397 1149 2446 1213!2446 1213[2481 1260 2481 1292!2481 1292[2481 1307 2472 1389!2472 1389[2472 #57C.C6 2465.5 1428"/>
                    <Edge fillStyle1="2" edges="
!2465.5 1428[#9A5.15 #597.64 2473 1434!2473 1434[#9A4.D8 #598.DE 2464.5 1432"/>
                    <Edge fillStyle1="7" edges="
!2464.5 1432[#99F.7B #59C.42 2462 1441!2462 1441[2451 1473 2451 1495!2451 1495[2451 1557 2372 1639!2372 1639[2265 1749 2097 1749!2097 1749[2030 1749 1865 1728!1865 1728[1713 1707 1710 1707!1710 1707[#6A1.DA 1707 1666.5 1671"/>
                    <Edge fillStyle1="2" edges="
!2058 1143[#816.5 #473.96 2082 1136!2082 1136[#819.B7 1135 2068 1135!2068 1135[#80F.47 1135 2058 1143"/>
                    <Edge fillStyle0="2" fillStyle1="4" edges="
!1759 1322[1740 1338 1711 1338!1711 1338[1685 1338 1674 1315!1674 1315[1668 1302 1668 1289!1668 1289[1668 1238 1723 1235!1723 1235[1777 1232 1777 1287!1777 1287[1777 1306 1759 1322"/>
                    <Edge fillStyle0="2" fillStyle1="7" edges="
!2465.5 1428[#9A1.0E #596.13 2464.5 1432"/>
                    <Edge fillStyle1="1" edges="
!1024 736[975 711 936 690!936 690[772 603 772 592!772 592[772 526 885 531!885 531[981 535 1132 588!1132 588[1272 637 1380 698!1380 698[1492 762 1492 797!1492 797[1492 847 1458 866!1458 866[1441 875 1413 879!1413 879[1405 880 1396 880
!1396 880[1389 880 1382 880!1382 880[1326 880 1162 805!1162 805[1117 784 1064 757!1064 757[1048 748 1032 740!1032 740[1028 738 1024 736"/>
                    <Edge fillStyle1="2" edges="
!1356.5 1523.5[#516.9B 1584 1228 1584!1228 1584|1185 1580.5!1185 1580.5[#487.6D 1582 1114 1582!1114 1582[891 1582 735 1501!735 1501[582 1422 582 1311!582 1311[#245.E5 #51C.04 582 1305!582 1305[577 #504.48 577 1266!577 1266[575 1172 610
 1079!610 1079[#278.14 #3FE.46 665.5 983!665.5 983[#2E8.C1 868 894 868!894 868[944 868 1055 925!1055 925[1113 956 1164 988!1164 988[1184 1001 1293 1051!1293 1051[#517.D5 #420.95 1313.5 1062"/>
                    <Edge fillStyle1="7" edges="
!1313.5 1062[#53C.44 #42D.4C 1373 1096!1373 1096[1470 1174 1470 1269!1470 1269[1470 #50E.D1 1458.5 1327.5!1458.5 1327.5[1459 #536.35 1459 1341!1459 1341[1459 1416 1413 1474!1413 1474[#56D.8A #5E0.52 1356.5 1523.5"/>
                    <Edge fillStyle0="2" fillStyle1="4" edges="
!754 1143[745 1123 745 1110!745 1110[745 1058 793 1066!793 1066[840 1074 840 1107!840 1107[840 1135 832 1149!832 1149[819 1170 784 1170!784 1170[766 1170 754 1143"/>
                    <Edge fillStyle0="2" fillStyle1="7" edges="
!1356.5 1523.5[#521.86 #60C.B3 1254.5 1555.5!1254.5 1555.5[#4B7.2E 1572 1152 1572!1152 1572[#474.67 1572 1128.5 1571!1128.5 1571[#461.D8 1572 1119 1572!1119 1572[#422.77 1572 988.5 1561!988.5 1561[#3D4.5 1567 973 1567!973 1567[#360.4D
 1567 755.5 1502.5!755.5 1502.5[633 #5B0.CE 633 1405!633 1405|634 1389!634 1389|637 1387!637 1387[#27E.BF #55F.33 661 1365!661 1365|690 1371!690 1371[690 1373 692 1380!692 1380[693 1388 688 1395!688 1395[#2B0.6C #573.D7 688.5 1397!688.5
 1397[#2B4.88 #576.E6 697 1401!697 1401[698 1401 869 1451!869 1451[#416.9E #5D9.6A 1173 1514.5!1173 1514.5[#4A9.57 #5E9.46 1211.5 1511.5!1211.5 1511.5[#4B6.C6 #5E1.8B 1206 1504!1206 1504[1203 1499 1203 1489!1203 1489[1203 1466 1287 1397
!1287 1397[1371 1329 1371 1284!1371 1284[1371 1225 1323 1151!1323 1151[1275 1087 1275 1080!1275 1080[1275 1054 1305 1060!1305 1060[#51D.29 #424.B1 1313.5 1062"/>
                    <Edge fillStyle0="4" fillStyle1="6" edges="
!1381 2310.5[1380 #8FB.3E 1380 2289!1380 2289[1380 2270 1422 2249!1422 2249[#5A3.0E #8BD.F9 1453.5 2240.5"/>
                    <Edge fillStyle0="4" fillStyle1="5" edges="
!1453.5 2240.5[#5FC.0F 2181 1615 2181!1615 2181[1792 2181 1869 2291!1869 2291[1920 2364 1920 2475!1920 2475|1915 2513!1915 2513[1906 2558 1889 2595!1889 2595[1833 2715 1709 2715!1709 2715[#6AB.66 2715 1706 2715"/>
                    <Edge fillStyle0="4" fillStyle1="6" edges="
!1706 2715[#6A3.97 2721 1688 2721!1688 2721[#65C.94 2721 1576.5 2684"/>
                    <Edge fillStyle0="4" fillStyle1="5" edges="
!1576.5 2684[#5DD.28 #A54.F7 1448 2556!1448 2556[1377 2437 1377 2322!1377 2322[1377 #90D.22 1381 2310.5"/>
                    <Edge fillStyle1="4" edges="
!1851 2265[1924 #924.5C 1924 2494!1924 2494[1924 2533 1898 2601!1898 2601[1872 2669 1872 2674!1872 2674[1872 2695 1843 2730!1843 2730[1806 2776 1756 2776!1756 2776[1737 2776 1706 2765!1706 2765[1675 2754 1658 2754!1658 2754[1496 2754
 1398 2562!1398 2562[1327 2425 1327 2328!1327 2328[1327 #903.9 1336 2290"/>
                    <Edge fillStyle1="3" edges="
!1336 2290|1004 2285!1004 2285[924 2261 924 2200!924 2200[924 2143 1071 2105!1071 2105[1214 2067 1394 2074!1394 2074[1523 2078 1621 2105!1621 2105[1715 2104 1844 2127!1844 2127[2004 2156 2119 2206!2119 2206[2244 2260 2244 2310!2244 2310
[2244 #916.C8 2241 2341"/>
                    <Edge fillStyle1="4" edges="
!2241 2341|2241 2342!2241 2342[2241 #935.B1 2230.5 2370.5!2230.5 2370.5|2230 2371"/>
                    <Edge fillStyle1="3" edges="
!2230 2371[2209 2405 2164 2405!2164 2405[2089 2405 2053 2371!2053 2371[2021 2327 1996 2304!1996 2304[#7C9.FA #8FE.1D 1992 2300.5"/>
                    <Edge fillStyle1="4" edges="
!1992 2300.5[#79C.4 #8E9.EC 1932 2278!1932 2278[#75E.84 #8DB.EE 1849.5 2262"/>
                    <Edge fillStyle1="3" edges="
!1849.5 2262[#73A.5 #8D7.6C 1851 2265"/>
                    <Edge fillStyle0="3" fillStyle1="4" edges="
!1336 2290[#540.A9 #8E0.EE 1361.5 2258.5!1361.5 2258.5[#4F7.09 #8CF.02 1144 2250!1144 2250[1134 2250 1099 2258!1099 2258[1067 2266 1065 2266!1065 2266[1039 2266 1028 2248!1028 2248[1020 2236 1020 2224!1020 2224[1020 2160 1170 2160!1170
 2160[1219 2160 1316 2162!1316 2162[1412 2164 1527 2164!1527 2164[1530 2164 1721 2169!1721 2169[1920 2177 1968 2190!1968 2190[2035 2209 2121 2248!2121 2248[#8BF.C2 #8FF.6B 2241 2341"/>
                    <Edge fillStyle0="5" fillStyle1="6" edges="
!1453.5 2240.5[1464 #8C3.0B 1464 2259!1464 2259[1464 2267 1458 2280!1458 2280[1452 2294 1452 2301!1452 2301|1467 2367!1467 2367[1482 2433 1482 2464!1482 2464[1482 2555 1598 2623!1598 2623[1606 2628 1677 2665!1677 2665[1713 2683 1713 2693
!1713 2693[1713 #A94.05 1706 2715!1615 2226[1621 2225 1621 2224!1621 2224[1675 2274 1706 2381!1706 2381[1745 2513 1767 2551!1767 2551|1764 2571!1764 2571[#6DE.56 #A0F.3F 1749 2576.5!1749 2576.5[#6D3.1C 2578 1740 2578!1740 2578[#6C9.D4
 2578 1734.5 2573.5!1734.5 2573.5[#6B3.A9 #9FC.7B 1678.5 2454!1678.5 2454[#67E.F7 #970.67 1644 2367!1644 2367[1644 #938.12 1645.5 2355!1645.5 2355[1609 #8BE.D4 1609 2238!1609 2238[1609 2229 1615 2226!1576.5 2684[#5E5.9E #A4C.AC 1455 2528
!1455 2528[#56C.89 #95B.F5 1381 2310.5"/>
                    <Edge fillStyle0="3" fillStyle1="4" edges="
!2230 2371[#8B4.88 #944.78 2227 2374!2227 2374[2213 2388 2194 2388!2194 2388[2187 2388 2077 2338!2077 2338[#7E9.FF #90A.B2 1992 2300.5!1849.5 2262[#738.8D #8D5.AC 1847.5 2261.5!1847.5 2261.5[#739.53 #8D7.4A 1851 2265"/>
                    <Edge cubics="!1004 2285(;937,2265 924,2227 924,2200q1004 2285Q924 2261q924 2200);"/>
                    <Edge cubics="!924 2200(;924,2096 1349,2029 1621,2105q924 2200Q924 2143q1071 2105Q1214 2067q1394 2074Q1523 2078q1621 2105);"/>
                    <Edge cubics="!1621 2105(;1862,2104 2244,2213 2244,2310q1621 2105Q1715 2104q1844 2127Q2004 2156q2119 2206Q2244 2260q2244 2310);"/>
                    <Edge cubics="!1228 1584(;1227,1584 1211,1583 1185,1581q1228 1584 1185 1581);"/>
                    <Edge cubics="!2464 1344(;2464,1355 2461,1382 2455,1416q2464 1344 2455 1416);"/>
                    <Edge cubics="!772 592(;772,402 1492,702 1492,797q772 592Q772 526q885 531Q981 535q1132 588Q1272 637q1380 698Q1492 762q1492 797);"/>
                    <Edge cubics="!1492 797(;1492,830 1481,853 1458,866q1492 797Q1492 847q1458 866);"/>
                    <Edge cubics="!1396 880(;1391,880 1387,880 1382,880q1396 880Q1389 880q1382 880);"/>
                    <Edge cubics="!1064 757(;1053,751 1043,745 1032,740q1064 757Q1048 748q1032 740);"/>
                    <Edge cubics="!1382 880(;1345,880 1275,856 1162,805q1382 880Q1326 880q1162 805);"/>
                    <Edge cubics="!1162 805(;1137,793 1102,776 1064,757q1162 805 1064 757);"/>
                    <Edge cubics="!1032 740(;1029,739 1027,737 1024,736q1032 740Q1028 738q1024 736);"/>
                    <Edge cubics="!1024 736(;991,719 962,704 936,690q1024 736Q975 711q936 690);"/>
                    <Edge cubics="!1413 879(;1408,880 1402,880 1396,880q1413 879Q1405 880q1396 880);"/>
                    <Edge cubics="!1458 866(;1447,872 1432,876 1413,879q1458 866Q1441 875q1413 879);"/>
                    <Edge cubics="!936 690(;827,632 772,599 772,592q936 690Q772 603q772 592);"/>
                    <Edge cubics="!2410 1536(;2357,1642 2285,1695 2194,1695q2410 1536Q2331 1695q2194 1695);"/>
                    <Edge cubics="!2473 1434(;2466,1432 2459,1430 2452,1429q2473 1434Q2462 1431q2452 1429);"/>
                    <Edge cubics="!2455 1416(;2460,1423 2466,1429 2473,1434q2455 1416Q2463 1427q2473 1434);"/>
                    <Edge cubics="!2452 1429(;2443,1462 2429,1497 2410,1536q2452 1429Q2438 1478q2410 1536);"/>
                    <Edge cubics="!577 1266(;576,1203 587,1141 610,1079q577 1266Q575 1172q610 1079);"/>
                    <Edge cubics="!610 1079(;625,1041 643,1009 666,983q610 1079Q632 1022q666 983);"/>
                    <Edge cubics="!1932 668(;1984,642 2041,619 2097,599q1932 668 2001 637 2097 599);"/>
                    <Edge cubics="!2097 599(;2244,547 2382,520 2408,549q2097 599Q2181 568q2259 551Q2385 523q2408 549);"/>
                    <Edge cubics="!2408 549(;2430,574 2438,598 2428,622q2408 549Q2442 586q2428 622);"/>
                    <Edge cubics="!2393 675(;2389,678 2386,681 2382,685q2393 675Q2387 680q2382 685);"/>
                    <Edge cubics="!2428 622(;2424,638 2412,656 2393,675q2428 622Q2422 646q2393 675);"/>
                    <Edge cubics="!2064 807(;2052,810 2040,812 2029,816q2064 807Q2046 811q2029 816);"/>
                    <Edge cubics="!2029 816(;1947,838 1882,855 1832,867q2029 816 1832 867);"/>
                    <Edge cubics="!1832 867(;1773,880 1740,885 1737,881q1832 867Q1743 887q1737 881);"/>
                    <Edge cubics="!2382 685(;2374,692 2362,700 2347,708q2382 685Q2370 696q2347 708);"/>
                    <Edge cubics="!2347 708(;2310,728 2250,751 2167,777q2347 708Q2290 739q2167 777);"/>
                    <Edge cubics="!2167 777(;2138,786 2103,796 2064,807q2167 777 2064 807);"/>
                    <Edge cubics="!1895 686(;1907,680 1919,674 1932,668q1895 686Q1913 677q1932 668);"/>
                    <Edge cubics="!1737 881(;1708,849 1722,809 1779,760q1737 881Q1693 833q1779 760);"/>
                    <Edge cubics="!1779 760(;1809,735 1848,710 1895,686q1779 760Q1824 722q1895 686);"/>
                    <Edge cubics="!894 868(;974,868 1153,981 1164,988q894 868Q944 868q1055 925Q1113 956q1164 988);"/>
                    <Edge cubics="!1114 1582(;813,1582 582,1457 582,1311q1114 1582Q891 1582q735 1501Q582 1422q582 1311);"/>
                    <Edge cubics="!666 983(;712,917 783,868 894,868q666 983Q745 868q894 868);"/>
                    <Edge cubics="!1956 1719(;1941,1719 1833,1713 1818,1713q1956 1719 1818 1713);"/>
                    <Edge cubics="!1818 1713(;1759,1713 1711,1698 1667,1671q1818 1713Q1731 1713q1667 1671);"/>
                    <Edge cubics="!1667 1671(;1556,1603 1524,1455 1524,1406q1667 1671Q1618 1640q1582 1584Q1524 1493q1524 1406);"/>
                    <Edge cubics="!2432 1236(;2311,1162 2050,1017 1815,1017q2432 1236 2283 1153Q2016 1017q1815 1017);"/>
                    <Edge cubics="!1815 1017(;1800,1017 1759,1017 1722,1026q1815 1017Q1759 1017q1722 1026);"/>
                    <Edge cubics="!1722 1026(;1704,1030 1682,1035 1653,1043q1722 1026 1653 1043);"/>
                    <Edge cubics="!840 1107(;840,1134 837,1170 784,1170q840 1107Q840 1135q832 1149Q819 1170q784 1170);"/>
                    <Edge cubics="!784 1170(;755,1170 745,1117 745,1110q784 1170Q766 1170q754 1143Q745 1123q745 1110);"/>
                    <Edge cubics="!745 1110(;745,1035 840,1069 840,1107q745 1110Q745 1058q793 1066Q840 1074q840 1107);"/>
                    <Edge cubics="!1777 1287(;1777,1311 1752,1338 1711,1338q1777 1287Q1777 1306q1759 1322Q1740 1338q1711 1338);"/>
                    <Edge cubics="!1711 1338(;1670,1338 1668,1293 1668,1289q1711 1338Q1685 1338q1674 1315Q1668 1302q1668 1289);"/>
                    <Edge cubics="!1668 1289(;1668,1223 1777,1212 1777,1287q1668 1289Q1668 1238q1723 1235Q1777 1232q1777 1287);"/>
                    <Edge cubics="!1851 2265(;1920,2341 1924,2442 1924,2494q1851 2265Q1924 2340q1924 2494);"/>
                    <Edge cubics="!1924 2494(;1924,2561 1872,2652 1872,2674q1924 2494Q1924 2533q1898 2601Q1872 2669q1872 2674);"/>
                    <Edge cubics="!1872 2674(;1872,2688 1834,2776 1756,2776q1872 2674Q1872 2695q1843 2730Q1806 2776q1756 2776);"/>
                    <Edge cubics="!1756 2776(;1719,2776 1692,2754 1658,2754q1756 2776Q1737 2776q1706 2765Q1675 2754q1658 2754);"/>
                    <Edge cubics="!1658 2754(;1405,2754 1327,2385 1327,2328q1658 2754Q1496 2754q1398 2562Q1327 2425q1327 2328);"/>
                    <Edge cubics="!1170 2160(;1290,2160 1319,2164 1527,2164q1170 2160Q1219 2160q1316 2162Q1412 2164q1527 2164);"/>
                    <Edge cubics="!1527 2164(;1533,2164 1891,2169 1968,2190q1527 2164Q1530 2164q1721 2169Q1920 2177q1968 2190);"/>
                    <Edge cubics="!1362 2259(;1258,2254 1145,2250 1144,2250q1362 2259 1144 2250);"/>
                    <Edge cubics="!1144 2250(;1127,2250 1068,2266 1065,2266q1144 2250Q1134 2250q1099 2258Q1067 2266q1065 2266);"/>
                    <Edge cubics="!1065 2266(;1025,2266 1020,2231 1020,2224q1065 2266Q1039 2266q1028 2248Q1020 2236q1020 2224);"/>
                    <Edge cubics="!1020 2224(;1020,2199 1038,2160 1170,2160q1020 2224Q1020 2160q1170 2160);"/>
                    <Edge cubics="!1615 2181(;1885,2181 1920,2375 1920,2475q1615 2181Q1792 2181q1869 2291Q1920 2364q1920 2475);"/>
                    <Edge cubics="!1920 2475(;1920,2475 1907,2715 1709,2715q1920 2475Q1920 2475q1915 2513Q1906 2558q1889 2595Q1833 2715q1709 2715);"/>
                    <Edge cubics="!1464 2259(;1464,2274 1452,2286 1452,2301q1464 2259Q1464 2267q1458 2280Q1452 2294q1452 2301);"/>
                    <Edge cubics="!1452 2301(;1452,2312 1482,2412 1482,2464q1452 2301Q1452 2301q1467 2367Q1482 2433q1482 2464);"/>
                    <Edge cubics="!1482 2464(;1482,2616 1713,2660 1713,2693q1482 2464Q1482 2555q1598 2623Q1606 2628q1677 2665Q1713 2683q1713 2693);"/>
                    <Edge cubics="!1621 2224(;1716,2313 1704,2445 1767,2551q1621 2224Q1675 2274q1706 2381Q1745 2513q1767 2551);"/>
                    <Edge cubics="!1767 2551(;1767,2551 1764,2571 1764,2571q1767 2551 1764 2571);"/>
                    <Edge cubics="!1609 2238(;1609,2223 1621,2226 1621,2224q1609 2238Q1609 2229q1615 2226Q1621 2225q1621 2224);"/>
                    <Edge cubics="!1152 1572(;1082,1572 1048,1552 1007,1552q1152 1572Q1113 1572q1069 1562Q1024 1552q1007 1552);"/>
                    <Edge cubics="!1007 1552(;992,1552 988,1567 973,1567q1007 1552Q1000 1552q990 1560Q981 1567q973 1567);"/>
                    <Edge cubics="!973 1567(;798,1567 637,1427 637,1389q973 1567Q856 1567q739 1492Q637 1427q637 1389);"/>
                    <Edge cubics="!637 1389(;637,1381 646,1372 661,1365q637 1389Q637 1376q661 1365);"/>
                    <Edge cubics="!661 1365(;661,1365 690,1371 690,1371q661 1365 690 1371);"/>
                    <Edge cubics="!690 1371(;690,1374 696,1383 688,1395q690 1371Q690 1373q692 1380Q693 1388q688 1395);"/>
                    <Edge cubics="!688 1395(;690,1399 682,1401 697,1401q688 1395Q689 1397q688 1400Q688 1401q697 1401);"/>
                    <Edge cubics="!697 1401(;699,1401 986,1494 1203,1518q697 1401Q698 1401q869 1451Q1068 1503q1203 1518);"/>
                    <Edge cubics="!1203 1518(;1203,1518 1215,1515 1215,1515q1203 1518 1215 1515);"/>
                    <Edge cubics="!1215 1515(;1207,1506 1203,1504 1203,1489q1215 1515Q1207 1506q1206 1504Q1203 1499q1203 1489);"/>
                    <Edge cubics="!1203 1489(;1203,1436 1371,1366 1371,1284q1203 1489Q1203 1466q1287 1397Q1371 1329q1371 1284);"/>
                    <Edge cubics="!1371 1284(;1371,1186 1275,1094 1275,1080q1371 1284Q1371 1225q1323 1151Q1275 1087q1275 1080);"/>
                    <Edge cubics="!2068 1135(;2065,1135 2061,1138 2058,1143q2068 1135Q2063 1135q2058 1143);"/>
                    <Edge cubics="!2082 1136(;2074,1139 2066,1141 2058,1143q2082 1136Q2070 1140q2058 1143);"/>
                    <Edge cubics="!2082 1136(;2077,1135 2072,1135 2068,1135q2082 1136Q2074 1135q2068 1135);"/>
                    <Edge cubics="!2194 1695(;2181,1695 2168,1693 2155,1688q2194 1695Q2174 1695q2155 1688);"/>
                    <Edge cubics="!2155 1688(;2097,1709 2031,1719 1956,1719q2155 1688Q2068 1719q1956 1719);"/>
                    <Edge cubics="!2432 1236(;2453,1263 2464,1299 2464,1344q2432 1236Q2464 1277q2464 1344);"/>
                    <Edge cubics="!582 1311(;582,1309 582,1307 582,1305q582 1311Q582 1308q582 1305);"/>
                    <Edge cubics="!582 1305(;579,1291 577,1278 577,1266q582 1305Q577 1284q577 1266);"/>
                    <Edge cubics="!1275 1080(;1275,1063 1285,1056 1305,1060q1275 1080Q1275 1054q1305 1060);"/>
                    <Edge cubics="!1305 1060(;1308,1061 1311,1061 1314,1062q1305 1060Q1309 1061q1314 1062);"/>
                    <Edge cubics="!1293 1051(;1300,1055 1307,1059 1314,1062q1293 1051Q1304 1057q1314 1062);"/>
                    <Edge cubics="!1314 1062(;1331,1067 1351,1078 1373,1096q1314 1062Q1340 1069q1373 1096);"/>
                    <Edge cubics="!1470 1269(;1470,1285 1467,1304 1459,1328q1470 1269Q1470 1295q1459 1328);"/>
                    <Edge cubics="!1459 1328(;1453,1346 1442,1370 1427,1396q1459 1328 1427 1396);"/>
                    <Edge cubics="!1427 1396(;1422,1405 1416,1415 1409,1426q1427 1396Q1419 1410q1409 1426);"/>
                    <Edge cubics="!1427 1396(;1423,1406 1419,1417 1414,1428q1427 1396Q1421 1411q1414 1428);"/>
                    <Edge cubics="!1373 1096(;1438,1148 1470,1206 1470,1269q1373 1096Q1470 1174q1470 1269);"/>
                    <Edge cubics="!1524 1406(;1522,1326 1536,1249 1566,1174q1524 1406Q1521 1286q1566 1174);"/>
                    <Edge cubics="!1185 1581(;1168,1582 1144,1582 1114,1582q1185 1581Q1159 1582q1114 1582);"/>
                    <Edge cubics="!1409 1426(;1368,1490 1317,1533 1255,1556q1409 1426Q1347 1523q1255 1556);"/>
                    <Edge cubics="!1255 1556(;1224,1566 1189,1572 1152,1572q1255 1556Q1207 1572q1152 1572);"/>
                    <Edge cubics="!1414 1428(;1398,1467 1379,1498 1357,1524q1414 1428Q1389 1487q1357 1524);"/>
                    <Edge cubics="!1357 1524(;1321,1563 1278,1584 1228,1584q1357 1524Q1303 1584q1228 1584);"/>
                    <Edge cubics="!1164 988(;1177,997 1220,1018 1293,1051q1164 988Q1184 1001q1293 1051);"/>
                    <Edge cubics="!1381 2311(;1380,2303 1380,2296 1380,2289q1381 2311Q1380 2299q1380 2289);"/>
                    <Edge cubics="!1377 2322(;1377,2319 1378,2315 1381,2311q1377 2322Q1377 2317q1381 2311);"/>
                    <Edge cubics="!1327 2328(;1327,2315 1330,2302 1336,2290q1327 2328Q1327 2308q1336 2290);"/>
                    <Edge cubics="!1336 2290(;1342,2279 1351,2268 1362,2259q1336 2290Q1345 2273q1362 2259);"/>
                    <Edge cubics="!1422 2249(;1436,2242 1447,2239 1454,2241q1422 2249Q1443 2238q1454 2241);"/>
                    <Edge cubics="!1454 2241(;1461,2242 1464,2248 1464,2259q1454 2241Q1464 2243q1464 2259);"/>
                    <Edge cubics="!1454 2241(;1506,2201 1560,2181 1615,2181q1454 2241Q1532 2181q1615 2181);"/>
                    <Edge cubics="!1380 2289(;1380,2276 1394,2263 1422,2249q1380 2289Q1380 2270q1422 2249);"/>
                    <Edge cubics="!1577 2684(;1532,2653 1492,2601 1455,2528q1577 2684Q1510 2637q1455 2528);"/>
                    <Edge cubics="!1577 2684(;1526,2658 1483,2615 1448,2556q1577 2684Q1501 2645q1448 2556);"/>
                    <Edge cubics="!1455 2528(;1411,2440 1386,2368 1381,2311q1455 2528Q1389 2396q1381 2311);"/>
                    <Edge cubics="!1448 2556(;1401,2477 1377,2399 1377,2322q1448 2556Q1377 2437q1377 2322);"/>
                    <Edge cubics="!1336 2290(;1336,2290 1004,2285 1004,2285q1336 2290 1004 2285);"/>
                    <Edge cubics="!2164 2405(;2114,2405 2077,2394 2053,2371q2164 2405Q2089 2405q2053 2371);"/>
                    <Edge cubics="!2194 2388(;2189,2388 2150,2371 2077,2338q2194 2388Q2187 2388q2077 2338);"/>
                    <Edge cubics="!2227 2374(;2218,2383 2207,2388 2194,2388q2227 2374Q2213 2388q2194 2388);"/>
                    <Edge cubics="!2241 2341(;2241,2341 2241,2342 2241,2342q2241 2341 2241 2342);"/>
                    <Edge cubics="!2244 2310(;2244,2321 2243,2332 2241,2341q2244 2310Q2244 2327q2241 2341);"/>
                    <Edge cubics="!2231 2371(;2231,2371 2230,2371 2230,2371q2231 2371 2230 2371);"/>
                    <Edge cubics="!2241 2342(;2241,2353 2238,2362 2231,2371q2241 2342Q2241 2358q2231 2371);"/>
                    <Edge cubics="!2121 2248(;2200,2285 2240,2316 2241,2341q2121 2248Q2240 2303q2241 2341);"/>
                    <Edge cubics="!2230 2371(;2216,2394 2194,2405 2164,2405q2230 2371Q2209 2405q2164 2405);"/>
                    <Edge cubics="!2230 2371(;2229,2372 2228,2373 2227,2374q2230 2371Q2229 2372q2227 2374);"/>
                    <Edge cubics="!1679 2454(;1668,2429 1657,2400 1644,2367q1679 2454Q1663 2416q1644 2367);"/>
                    <Edge cubics="!1644 2367(;1644,2362 1645,2358 1646,2355q1644 2367Q1644 2360q1646 2355);"/>
                    <Edge cubics="!1992 2301(;1963,2288 1943,2281 1932,2278q1992 2301Q1948 2282q1932 2278);"/>
                    <Edge cubics="!1996 2304(;1995,2303 1993,2302 1992,2301q1996 2304Q1994 2302q1992 2301);"/>
                    <Edge cubics="!1848 2262(;1849,2263 1850,2264 1851,2265q1848 2262Q1849 2263q1851 2265);"/>
                    <Edge cubics="!1850 2262(;1850,2263 1850,2264 1851,2265q1850 2262Q1850 2263q1851 2265);"/>
                    <Edge cubics="!1932 2278(;1902,2271 1875,2266 1850,2262q1932 2278Q1887 2268q1850 2262);"/>
                    <Edge cubics="!1850 2262(;1849,2262 1849,2262 1848,2262q1850 2262Q1849 2262q1848 2262);"/>
                    <Edge cubics="!1749 2577(;1748,2578 1745,2578 1740,2578q1749 2577Q1747 2578q1740 2578);"/>
                    <Edge cubics="!1740 2578(;1739,2578 1737,2577 1735,2574q1740 2578Q1738 2578q1735 2574);"/>
                    <Edge cubics="!1764 2571(;1760,2574 1755,2576 1749,2577q1764 2571Q1758 2575q1749 2577);"/>
                    <Edge cubics="!1709 2715(;1708,2715 1707,2715 1706,2715q1709 2715Q1707 2715q1706 2715);"/>
                    <Edge cubics="!1713 2693(;1713,2703 1711,2710 1706,2715q1713 2693Q1713 2708q1706 2715);"/>
                    <Edge cubics="!1706 2715(;1702,2719 1696,2721 1688,2721q1706 2715Q1700 2721q1688 2721);"/>
                    <Edge cubics="!1735 2574(;1722,2562 1704,2522 1679,2454q1735 2574Q1716 2556q1679 2454);"/>
                    <Edge cubics="!1968 2190(;2013,2203 2064,2222 2121,2248q1968 2190Q2035 2209q2121 2248);"/>
                    <Edge cubics="!2077 2338(;2043,2323 2015,2310 1992,2301q2077 2338Q2026 2315q1992 2301);"/>
                    <Edge cubics="!2053 2371(;2032,2342 2013,2319 1996,2304q2053 2371Q2021 2327q1996 2304);"/>
                    <Edge cubics="!1646 2355(;1621,2278 1609,2239 1609,2238q1646 2355Q1609 2239q1609 2238);"/>
                    <Edge cubics="!1688 2721(;1649,2721 1612,2709 1577,2684q1688 2721Q1629 2721q1577 2684);"/>
                    <Edge cubics="!1566 1174(;1588,1121 1617,1077 1653,1043q1566 1174Q1599 1094q1653 1043);"/>
                    <Edge cubics="!2320 1149(;2440,1149 2481,1272 2481,1292q2320 1149Q2397 1149q2446 1213Q2481 1260q2481 1292);"/>
                    <Edge cubics="!2481 1292(;2481,1307 2472,1374 2472,1389q2481 1292Q2481 1307q2472 1389);"/>
                    <Edge cubics="!2472 1389(;2472,1430 2451,1452 2451,1495q2472 1389Q2472 1409q2462 1441Q2451 1473q2451 1495);"/>
                    <Edge cubics="!2451 1495(;2451,1540 2357,1749 2097,1749q2451 1495Q2451 1557q2372 1639Q2265 1749q2097 1749);"/>
                    <Edge cubics="!2097 1749(;1989,1749 1716,1707 1710,1707q2097 1749Q2030 1749q1865 1728Q1713 1707q1710 1707);"/>
                    <Edge cubics="!1710 1707(;1689,1707 1630,1626 1630,1623q1710 1707Q1697 1707q1662 1666Q1630 1628q1630 1623);"/>
                    <Edge cubics="!1630 1623(;1630,1605 1651,1602 1656,1602q1630 1623Q1630 1611q1641 1606Q1649 1602q1656 1602);"/>
                    <Edge cubics="!1656 1602(;1695,1602 1777,1656 1834,1656q1656 1602Q1673 1602q1738 1629Q1803 1656q1834 1656);"/>
                    <Edge cubics="!1834 1656(;1914,1656 2129,1638 2154,1638q1834 1656Q1881 1656q2015 1647Q2148 1638q2154 1638);"/>
                    <Edge cubics="!2154 1638(;2319,1638 2373,1397 2373,1386q2154 1638Q2258 1638q2325 1516Q2373 1430q2373 1386);"/>
                    <Edge cubics="!2373 1386(;2373,1332 2353,1342 2356,1273q2373 1386Q2373 1362q2363 1335Q2354 1310q2356 1273);"/>
                    <Edge cubics="!2356 1273(;2328,1211 2262,1191 2262,1182q2356 1273Q2339 1236q2299 1208Q2262 1182q2262 1182);"/>
                    <Edge cubics="!2262 1182(;2262,1169 2267,1149 2320,1149q2262 1182Q2262 1149q2320 1149);"/>
                    <Edge cubics="!1459 1341(;1459,1386 1441,1470 1357,1524q1459 1341Q1459 1416q1413 1474Q1390 1504q1357 1524);"/>
                    <Edge cubics="!1357 1524(;1332,1537 1298,1550 1255,1556q1357 1524Q1314 1549q1255 1556);"/>
                    <Edge cubics="!1255 1556(;1245,1557 1227,1558 1208,1558q1255 1556 1208 1558);"/>
                    <Edge cubics="!1208 1558(;1193,1558 1134,1572 1119,1572q1208 1558Q1201 1558q1164 1565Q1127 1572q1119 1572);"/>
                    <Edge cubics="!1119 1572(;1087,1572 1043,1568 989,1561q1119 1572 989 1561);"/>
                    <Edge cubics="!989 1561(;915,1549 829,1529 756,1503q989 1561 826 1525 756 1503);"/>
                    <Edge cubics="!756 1503(;687,1477 633,1443 633,1405q756 1503Q633 1457q633 1405);"/>
                    <Edge cubics="!633 1405(;633,1390 634,1389 634,1389q633 1405 634 1389);"/>
                    <Edge cubics="!634 1389(;637,1389 637,1383 652,1383q634 1389Q634 1389q639 1386Q643 1383q652 1383);"/>
                    <Edge cubics="!652 1383(;684,1383 835,1516 1107,1516q652 1383Q668 1383q790 1450Q941 1516q1107 1516);"/>
                    <Edge cubics="!1107 1516(;1148,1516 1183,1514 1212,1512q1107 1516 1212 1512);"/>
                    <Edge cubics="!1212 1512(;1379,1495 1404,1434 1404,1341q1212 1512Q1310 1501q1353 1470Q1404 1433q1404 1341);"/>
                    <Edge cubics="!1404 1341(;1404,1252 1338,1141 1338,1125q1404 1341Q1404 1287q1371 1206Q1338 1133q1338 1125);"/>
                    <Edge cubics="!1338 1125(;1338,1056 1459,1205 1459,1341q1338 1125Q1338 1100q1357 1111Q1375 1121q1399 1156Q1459 1247q1459 1341);"/>
                  </edges>
                </DOMShape>
              </elements>
            </DOMFrame>
          </frames>
        </DOMLayer>
        <DOMLayer name="Layer 2" color="#9933CC">
          <frames>
            <DOMFrame index="0" keyMode="9728">
              <elements>
                <DOMGroup>
                  <transformationPoint>
                    <Point x="80.8" y="85.75"/>
                  </transformationPoint>
                  <members>
                    <DOMShape>
                      <transformationPoint>
                        <Point x="80.8" y="85.75"/>
                      </transformationPoint>
                      <fills>
                        <FillStyle index="1">
                          <SolidColor color="#ECD079" alpha="0.976470588235294"/>
                        </FillStyle>
                        <FillStyle index="2">
                          <SolidColor color="#E1C36A" alpha="0.976470588235294"/>
                        </FillStyle>
                        <FillStyle index="3">
                          <SolidColor color="#E3BF52" alpha="0.976470588235294"/>
                        </FillStyle>
                      </fills>
                      <edges>
                        <Edge fillStyle1="1" edges="
!1543 186[1635 129 1767 61!1767 61[2023 -72 2211 84!2211 84[2231 101 2347 220!2347 220[2423 297 2478 314!2478 314[2688 387 2747 511!2747 511[2764 546 2793 629!2793 629[2824 709 2870 772!2870 772[2982 921 3124 1047!3124 1047[3189 1105
 3189 1198!3189 1198|3189 1267!3189 1267[3229 1381 3229 1563!3229 1563[3229 1568 3232 1627!3232 1627[3231 1685 3217 1728"/>
                        <Edge fillStyle1="3" edges="
!3217 1728[3229 1802 3229 1865!3229 1865[3229 1951 3172 2161!3172 2161[3095 2452 2963 2694!2963 2694[2563 3430 1847 3430!1847 3430[739 3430 287 2819!287 2819[27 2468 27 2011!27 2011[27 1917 53 1789"/>
                        <Edge fillStyle1="1" edges="
!53 1789[0 1529 0 1424!0 1424[0 1402 69 1237!69 1237[151 1041 247 865!247 865[533 334 744 334!744 334[865 334 969 352"/>
                        <Edge fillStyle1="3" edges="
!969 352[1220 206 1515 188!1515 188[1530 186 1543 186"/>
                        <Edge fillStyle0="1" fillStyle1="2" edges="
!1908 585[1916 581 1947 573!1947 573|1967 613!1967 613[1955 650 1914 666!1914 666[1880 653 1860 633!1860 633[1884 598 1908 585!1648 1224[1636 1261 1595 1277!1595 1277[1561 1264 1542 1244!1542 1244[1565 1210 1589 1196!1589 1196[1597 1192
 1628 1184!1628 1184|1648 1224!2671 1211[2718 1211 2758 1251!2758 1251[2743 1260 2707 1243!2707 1243[2671 1227 2671 1211!2711 1649[2699 1687 2658 1703!2658 1703[2625 1689 2605 1669!2605 1669[2629 1635 2653 1622!2653 1622[2660 1618 2691
 1610!2691 1610|2711 1649!2578 1882[2602 1847 2626 1834!2626 1834[2634 1830 2664 1822!2664 1822|2684 1862!2684 1862[2672 1899 2631 1915!2631 1915[2598 1902 2578 1882"/>
                        <Edge fillStyle0="3" fillStyle1="1" edges="
!3217 1728[3216 1733 3213 1739!3213 1739[3183 1818 3110 1830!3110 1830[3110 1834 3110 1838!3110 1838[3110 2367 2970 2666!2970 2666[2688 3271 1874 3271!1874 3271[1717 3271 1664 3220!1664 3220[1631 3162 1588 3145!1588 3145[1496 3236 1490
 3242!1490 3242[1382 3324 1262 3324!1262 3324[1110 3324 1019 3202!1019 3202[979 3137 961 3111!961 3111[932 3066 904 3058!904 3058[761 3030 699 3013!699 3013[589 2982 585 2912!585 2912[577 2804 461 2679!461 2679[310 2537 232 2460!232 2460
[194 2422 98 1996!98 1996[72 1882 53 1789!969 352[1047 366 1115 391!1115 391[1193 419 1236 447!1236 447[1314 382 1397 290!1397 290[1447 245 1543 186"/>
                        <Edge fillStyle0="1" fillStyle1="2" edges="
!904 852[892 889 850 905!850 905[817 892 797 872!797 872[821 837 845 824!845 824[853 820 884 812!884 812|904 852!724 520|744 560!744 560[732 597 691 613!691 613[658 600 638 580!638 580[662 545 686 532!686 532[694 528 724 520!372 1490
[360 1527 319 1543!319 1543[286 1530 266 1510!266 1510[290 1475 314 1462!314 1462[322 1458 352 1450!352 1450|372 1490!1415 1370|1435 1410!1435 1410[1423 1447 1382 1463!1382 1463[1349 1450 1329 1430!1329 1430[1353 1396 1377 1382!1377 1382
[1385 1378 1415 1370!844 1171|880 1171!880 1171[918 1174 990 1191!990 1191[979 1223 957 1231!957 1231[857 1224 844 1204!844 1204|844 1171!1405 1808[1374 1794 1355 1776!1355 1776[1379 1741 1403 1728!1403 1728[1411 1724 1442 1716!1442 1716
|1462 1756!1462 1756[1452 1784 1429 1800!1429 1800[1434 1798 1442 1796!1442 1796|1462 1836!1462 1836[1450 1873 1409 1889!1409 1889[1375 1875 1355 1855!1355 1855[1379 1821 1403 1808!1403 1808|1405 1808!1522 2194|1542 2234!1542 2234[1530
 2271 1488 2287!1488 2287[1455 2274 1435 2254!1435 2254[1459 2220 1483 2206!1483 2206[1491 2202 1522 2194"/>
                        <Edge fillStyle0="3" fillStyle1="1" edges="
!1216 2327|1468 2327!1468 2327|1542 2294!1542 2294[1512 2294 1431 2305!1431 2305[1350 2314 1276 2314!1276 2314[1262 2313 1248 2313!1248 2313[1220 2315 1216 2327"/>
                        <Edge fillStyle0="1" fillStyle1="2" edges="
!1090 2713[1056 2699 1037 2679!1037 2679[1060 2645 1084 2632!1084 2632[1092 2628 1123 2620!1123 2620|1143 2659!1143 2659[1131 2697 1090 2713!611 2154[599 2192 558 2208!558 2208[525 2194 505 2174!505 2174[529 2140 553 2127!553 2127[561
 2123 591 2115!591 2115|611 2154!2585 2194|2605 2234!2605 2234[2593 2271 2552 2287!2552 2287[2518 2274 2498 2254!2498 2254[2522 2220 2546 2206!2546 2206[2554 2202 2585 2194!1920 2460|1940 2500!1940 2500[1928 2537 1887 2553!1887 2553[1854
 2540 1834 2520!1834 2520[1858 2485 1882 2472!1882 2472[1890 2468 1920 2460!1967 2128[1955 2165 1914 2181!1914 2181[1880 2168 1860 2148!1860 2148[1884 2113 1908 2100!1908 2100[1916 2096 1947 2088!1947 2088|1967 2128!2106 2620|2126 2659
!2126 2659[2114 2697 2073 2713!2073 2713[2040 2699 2020 2679!2020 2679[2044 2645 2068 2632!2068 2632[2076 2628 2106 2620"/>
                        <Edge cubics="!3229 1865(;3229,1988 2981,3430 1847,3430q3229 1865Q3229 1951q3172 2161Q3095 2452q2963 2694Q2563 3430q1847 3430);"/>
                        <Edge cubics="!1847 3430(;113,3430 27,2274 27,2011q1847 3430Q739 3430q287 2819Q27 2468q27 2011);"/>
                        <Edge cubics="!3110 1838(;3110,2137 3150,3271 1874,3271q3110 1838Q3110 2367q2970 2666Q2688 3271q1874 3271);"/>
                        <Edge cubics="!1874 3271(;1612,3271 1672,3178 1588,3145q1874 3271Q1717 3271q1664 3220Q1631 3162q1588 3145);"/>
                        <Edge cubics="!1588 3145(;1568,3164 1452,3324 1262,3324q1588 3145Q1496 3236q1490 3242Q1382 3324q1262 3324);"/>
                        <Edge cubics="!1262 3324(;1003,3324 994,3085 904,3058q1262 3324Q1110 3324q1019 3202Q979 3137q961 3111Q932 3066q904 3058);"/>
                        <Edge cubics="!904 3058(;775,3018 591,3025 585,2912q904 3058Q761 3030q699 3013Q589 2982q585 2912);"/>
                        <Edge cubics="!585 2912(;571,2742 385,2613 232,2460q585 2912Q577 2804q461 2679Q310 2537q232 2460);"/>
                        <Edge cubics="!0 1424(;0,1386 409,334 744,334q0 1424Q0 1402q69 1237Q151 1041q247 865Q533 334q744 334);"/>
                        <Edge cubics="!1767 61(;2190,-158 2290,257 2478,314q1767 61Q2023 -72q2211 84Q2231 101q2347 220Q2423 297q2478 314);"/>
                        <Edge cubics="!2478 314(;2828,436 2715,562 2870,772q2478 314Q2688 387q2747 511Q2764 546q2793 629Q2824 709q2870 772);"/>
                        <Edge cubics="!2870 772(;3123,1111 3189,1025 3189,1198q2870 772Q2982 921q3124 1047Q3189 1105q3189 1198);"/>
                        <Edge cubics="!1276 2314(;1276,2314 1223,2307 1216,2327q1276 2314Q1262 2313q1248 2313Q1220 2315q1216 2327);"/>
                        <Edge cubics="!1216 2327(;1216,2327 1468,2327 1468,2327q1216 2327 1468 2327);"/>
                        <Edge cubics="!1468 2327(;1468,2327 1542,2294 1542,2294q1468 2327 1542 2294);"/>
                        <Edge cubics="!1542 2294(;1468,2294 1409,2314 1276,2314q1542 2294Q1512 2294q1431 2305Q1350 2314q1276 2314);"/>
                        <Edge cubics="!990 1191(;983,1211 977,1224 957,1231q990 1191Q979 1223q957 1231);"/>
                        <Edge cubics="!957 1231(;957,1231 857,1224 844,1204q957 1231Q857 1224q844 1204);"/>
                        <Edge cubics="!844 1204(;844,1204 844,1171 844,1171q844 1204 844 1171);"/>
                        <Edge cubics="!844 1171(;857,1171 877,1164 990,1191q844 1171Q880 1171q880 1171Q918 1174q990 1191);"/>
                        <Edge cubics="!1947 573(;1947,573 1967,613 1967,613q1947 573 1967 613);"/>
                        <Edge cubics="!1967 613(;1960,633 1947,653 1914,666q1967 613Q1955 650q1914 666);"/>
                        <Edge cubics="!1914 666(;1914,666 1880,653 1860,633q1914 666Q1880 653q1860 633);"/>
                        <Edge cubics="!1860 633(;1898,580 1920,580 1947,573q1860 633Q1884 598q1908 585Q1916 581q1947 573);"/>
                        <Edge cubics="!1522 2194(;1522,2194 1542,2234 1542,2234q1522 2194 1542 2234);"/>
                        <Edge cubics="!1542 2234(;1535,2254 1522,2274 1488,2287q1542 2234Q1530 2271q1488 2287);"/>
                        <Edge cubics="!1488 2287(;1488,2287 1455,2274 1435,2254q1488 2287Q1455 2274q1435 2254);"/>
                        <Edge cubics="!1435 2254(;1472,2201 1495,2201 1522,2194q1435 2254Q1459 2220q1483 2206Q1491 2202q1522 2194);"/>
                        <Edge cubics="!1415 1370(;1415,1370 1435,1410 1435,1410q1415 1370 1435 1410);"/>
                        <Edge cubics="!1435 1410(;1429,1430 1415,1450 1382,1463q1435 1410Q1423 1447q1382 1463);"/>
                        <Edge cubics="!1382 1463(;1382,1463 1349,1450 1329,1430q1382 1463Q1349 1450q1329 1430);"/>
                        <Edge cubics="!1329 1430(;1366,1377 1389,1377 1415,1370q1329 1430Q1353 1396q1377 1382Q1385 1378q1415 1370);"/>
                        <Edge cubics="!591 2115(;591,2115 611,2154 611,2154q591 2115 611 2154);"/>
                        <Edge cubics="!611 2154(;605,2174 591,2194 558,2208q611 2154Q599 2192q558 2208);"/>
                        <Edge cubics="!558 2208(;558,2208 525,2194 505,2174q558 2208Q525 2194q505 2174);"/>
                        <Edge cubics="!505 2174(;542,2121 565,2121 591,2115q505 2174Q529 2140q553 2127Q561 2123q591 2115);"/>
                        <Edge cubics="!1442 1796(;1442,1796 1462,1836 1462,1836q1442 1796 1462 1836);"/>
                        <Edge cubics="!1462 1836(;1455,1855 1442,1875 1409,1889q1462 1836Q1450 1873q1409 1889);"/>
                        <Edge cubics="!1409 1889(;1409,1889 1375,1875 1355,1855q1409 1889Q1375 1875q1355 1855);"/>
                        <Edge cubics="!2585 2194(;2585,2194 2605,2234 2605,2234q2585 2194 2605 2234);"/>
                        <Edge cubics="!2605 2234(;2598,2254 2585,2274 2552,2287q2605 2234Q2593 2271q2552 2287);"/>
                        <Edge cubics="!2552 2287(;2552,2287 2518,2274 2498,2254q2552 2287Q2518 2274q2498 2254);"/>
                        <Edge cubics="!2498 2254(;2536,2201 2558,2201 2585,2194q2498 2254Q2522 2220q2546 2206Q2554 2202q2585 2194);"/>
                        <Edge cubics="!1920 2460(;1920,2460 1940,2500 1940,2500q1920 2460 1940 2500);"/>
                        <Edge cubics="!1940 2500(;1934,2520 1920,2540 1887,2553q1940 2500Q1928 2537q1887 2553);"/>
                        <Edge cubics="!1887 2553(;1887,2553 1854,2540 1834,2520q1887 2553Q1854 2540q1834 2520);"/>
                        <Edge cubics="!1834 2520(;1871,2467 1894,2467 1920,2460q1834 2520Q1858 2485q1882 2472Q1890 2468q1920 2460);"/>
                        <Edge cubics="!1123 2620(;1123,2620 1143,2659 1143,2659q1123 2620 1143 2659);"/>
                        <Edge cubics="!1143 2659(;1136,2679 1123,2699 1090,2713q1143 2659Q1131 2697q1090 2713);"/>
                        <Edge cubics="!1090 2713(;1090,2713 1056,2699 1037,2679q1090 2713Q1056 2699q1037 2679);"/>
                        <Edge cubics="!1037 2679(;1074,2626 1096,2626 1123,2620q1037 2679Q1060 2645q1084 2632Q1092 2628q1123 2620);"/>
                        <Edge cubics="!2106 2620(;2106,2620 2126,2659 2126,2659q2106 2620 2126 2659);"/>
                        <Edge cubics="!2126 2659(;2120,2679 2106,2699 2073,2713q2126 2659Q2114 2697q2073 2713);"/>
                        <Edge cubics="!2073 2713(;2073,2713 2040,2699 2020,2679q2073 2713Q2040 2699q2020 2679);"/>
                        <Edge cubics="!2020 2679(;2057,2626 2080,2626 2106,2620q2020 2679Q2044 2645q2068 2632Q2076 2628q2106 2620);"/>
                        <Edge cubics="!2664 1822(;2664,1822 2684,1862 2684,1862q2664 1822 2684 1862);"/>
                        <Edge cubics="!2684 1862(;2678,1882 2664,1902 2631,1915q2684 1862Q2672 1899q2631 1915);"/>
                        <Edge cubics="!2631 1915(;2631,1915 2598,1902 2578,1882q2631 1915Q2598 1902q2578 1882);"/>
                        <Edge cubics="!2578 1882(;2615,1829 2638,1829 2664,1822q2578 1882Q2602 1847q2626 1834Q2634 1830q2664 1822);"/>
                        <Edge cubics="!2758 1251(;2738,1264 2671,1231 2671,1211q2758 1251Q2743 1260q2707 1243Q2671 1227q2671 1211);"/>
                        <Edge cubics="!2671 1211(;2684,1211 2718,1211 2758,1251q2671 1211Q2718 1211q2758 1251);"/>
                        <Edge cubics="!724 520(;724,520 744,560 744,560q724 520 744 560);"/>
                        <Edge cubics="!744 560(;737,580 724,600 691,613q744 560Q732 597q691 613);"/>
                        <Edge cubics="!691 613(;691,613 658,600 638,580q691 613Q658 600q638 580);"/>
                        <Edge cubics="!638 580(;675,527 698,527 724,520q638 580Q662 545q686 532Q694 528q724 520);"/>
                        <Edge cubics="!352 1450(;352,1450 372,1490 372,1490q352 1450 372 1490);"/>
                        <Edge cubics="!372 1490(;365,1510 352,1530 319,1543q372 1490Q360 1527q319 1543);"/>
                        <Edge cubics="!319 1543(;319,1543 286,1530 266,1510q319 1543Q286 1530q266 1510);"/>
                        <Edge cubics="!266 1510(;303,1457 326,1457 352,1450q266 1510Q290 1475q314 1462Q322 1458q352 1450);"/>
                        <Edge cubics="!1442 1716(;1442,1716 1462,1756 1462,1756q1442 1716 1462 1756);"/>
                        <Edge cubics="!1355 1776(;1393,1723 1415,1723 1442,1716q1355 1776Q1379 1741q1403 1728Q1411 1724q1442 1716);"/>
                        <Edge cubics="!1947 2088(;1947,2088 1967,2128 1967,2128q1947 2088 1967 2128);"/>
                        <Edge cubics="!1967 2128(;1960,2148 1947,2168 1914,2181q1967 2128Q1955 2165q1914 2181);"/>
                        <Edge cubics="!1914 2181(;1914,2181 1880,2168 1860,2148q1914 2181Q1880 2168q1860 2148);"/>
                        <Edge cubics="!1860 2148(;1898,2095 1920,2095 1947,2088q1860 2148Q1884 2113q1908 2100Q1916 2096q1947 2088);"/>
                        <Edge cubics="!2691 1610(;2691,1610 2711,1649 2711,1649q2691 1610 2711 1649);"/>
                        <Edge cubics="!2711 1649(;2704,1669 2691,1689 2658,1703q2711 1649Q2699 1687q2658 1703);"/>
                        <Edge cubics="!2658 1703(;2658,1703 2625,1689 2605,1669q2658 1703Q2625 1689q2605 1669);"/>
                        <Edge cubics="!2605 1669(;2642,1616 2664,1616 2691,1610q2605 1669Q2629 1635q2653 1622Q2660 1618q2691 1610);"/>
                        <Edge cubics="!1628 1184(;1628,1184 1648,1224 1648,1224q1628 1184 1648 1224);"/>
                        <Edge cubics="!1648 1224(;1641,1244 1628,1264 1595,1277q1648 1224Q1636 1261q1595 1277);"/>
                        <Edge cubics="!1595 1277(;1595,1277 1561,1264 1542,1244q1595 1277Q1561 1264q1542 1244);"/>
                        <Edge cubics="!1542 1244(;1579,1191 1601,1191 1628,1184q1542 1244Q1565 1210q1589 1196Q1597 1192q1628 1184);"/>
                        <Edge cubics="!884 812(;884,812 904,852 904,852q884 812 904 852);"/>
                        <Edge cubics="!904 852(;897,872 884,892 850,905q904 852Q892 889q850 905);"/>
                        <Edge cubics="!850 905(;850,905 817,892 797,872q850 905Q817 892q797 872);"/>
                        <Edge cubics="!797 872(;835,819 857,819 884,812q797 872Q821 837q845 824Q853 820q884 812);"/>
                        <Edge cubics="!1543 186(;1604,148 1678,107 1767,61q1543 186Q1635 129q1767 61);"/>
                        <Edge cubics="!1515 188(;1524,186 1534,186 1543,186q1515 188Q1530 186q1543 186);"/>
                        <Edge cubics="!969 352(;1021,362 1070,374 1115,391q969 352Q1047 366q1115 391);"/>
                        <Edge cubics="!1115 391(;1167,410 1208,428 1236,447q1115 391Q1193 419q1236 447);"/>
                        <Edge cubics="!1236 447(;1288,403 1342,351 1397,290q1236 447Q1314 382q1397 290);"/>
                        <Edge cubics="!1397 290(;1430,259 1479,225 1543,186q1397 290Q1447 245q1543 186);"/>
                        <Edge cubics="!969 352(;1136,255 1318,200 1515,188q969 352Q1220 206q1515 188);"/>
                        <Edge cubics="!744 334(;825,334 900,340 969,352q744 334Q865 334q969 352);"/>
                        <Edge cubics="!1429 1800(;1433,1798 1437,1797 1442,1796q1429 1800Q1434 1798q1442 1796);"/>
                        <Edge cubics="!1405 1808(;1385,1798 1367,1788 1355,1776q1405 1808Q1374 1794q1355 1776);"/>
                        <Edge cubics="!1403 1808(;1403,1808 1405,1808 1405,1808q1403 1808 1405 1808);"/>
                        <Edge cubics="!1355 1855(;1371,1833 1387,1817 1403,1808q1355 1855Q1379 1821q1403 1808);"/>
                        <Edge cubics="!1462 1756(;1455,1774 1444,1789 1429,1800q1462 1756Q1452 1784q1429 1800);"/>
                        <Edge cubics="!53 1789(;17,1615 0,1494 0,1424q53 1789Q0 1529q0 1424);"/>
                        <Edge cubics="!232 2460(;207,2435 162,2279 98,1996q232 2460Q194 2422q98 1996);"/>
                        <Edge cubics="!27 2011(;27,1948 36,1874 53,1789q27 2011Q27 1917q53 1789);"/>
                        <Edge cubics="!98 1996(;81,1921 65,1851 53,1789q98 1996Q72 1882q53 1789);"/>
                        <Edge cubics="!3189 1198(;3189,1198 3189,1267 3189,1267q3189 1198 3189 1267);"/>
                        <Edge cubics="!3232 1627(;3231,1665 3227,1700 3217,1728q3232 1627Q3231 1685q3217 1728);"/>
                        <Edge cubics="!3213 1739(;3193,1792 3159,1822 3110,1830q3213 1739Q3183 1818q3110 1830);"/>
                        <Edge cubics="!3217 1728(;3225,1777 3229,1824 3229,1865q3217 1728Q3229 1802q3229 1865);"/>
                        <Edge cubics="!3217 1728(;3216,1732 3215,1735 3213,1739q3217 1728Q3216 1733q3213 1739);"/>
                        <Edge cubics="!3110 1830(;3110,1833 3110,1836 3110,1838q3110 1830Q3110 1834q3110 1838);"/>
                        <Edge cubics="!3229 1563(;3229,1567 3231,1588 3232,1627q3229 1563Q3229 1568q3232 1627);"/>
                        <Edge cubics="!3189 1267(;3216,1342 3229,1442 3229,1563q3189 1267Q3229 1381q3229 1563);"/>
                      </edges>
                    </DOMShape>
                  </members>
                </DOMGroup>
              </elements>
            </DOMFrame>
          </frames>
        </DOMLayer>
      </layers>
    </DOMTimeline>
  </timeline>
</DOMSymbolItem>